 {
  "entries": [   
    {
      "item": "chisel:bricks|0",
      "emc": 64
    },
    {
      "item": "chisel:bricks|1",
      "emc": 64
    },
    {
      "item": "chisel:bricks|2",
      "emc": 64
    },
    {
      "item": "chisel:bricks|3",
      "emc": 64
    },
    {
      "item": "chisel:bricks|4",
      "emc": 64
    },
    {
      "item": "chisel:bricks|5",
      "emc": 64
    },
    {
      "item": "chisel:bricks|6",
      "emc": 64
    },
    {
      "item": "chisel:bricks|7",
      "emc": 64
    },
    {
      "item": "chisel:bricks|8",
      "emc": 64
    },
    {
      "item": "chisel:bricks|9",
      "emc": 64
    },
    {
      "item": "chisel:bricks|10",
      "emc": 64
    },
    {
      "item": "chisel:bricks|11",
      "emc": 64
    },
    {
      "item": "chisel:bricks|12",
      "emc": 64
    },
    {
      "item": "chisel:bricks|13",
      "emc": 64
    },
    {
      "item": "chisel:bricks|14",
      "emc": 64
    },
    {
      "item": "chisel:bricks|15",
      "emc": 64
    },
    {
      "item": "chisel:bricks1|0",
      "emc": 64
    },
    {
      "item": "chisel:bricks1|1",
      "emc": 64
    },
    {
      "item": "chisel:bricks1|2",
      "emc": 64
    },
    {
      "item": "chisel:bricks1|3",
      "emc": 64
    },
    {
      "item": "chisel:bricks1|4",
      "emc": 64
    },
    {
      "item": "chisel:bricks1|5",
      "emc": 64
    },
    {
      "item": "chisel:bricks1|6",
      "emc": 64
    },
    {
      "item": "chisel:bricks1|7",
      "emc": 64
    },
    {
      "item": "chisel:bricks1|8",
      "emc": 64
    },
    {
      "item": "chisel:bricks1|9",
      "emc": 64
    },
    {
      "item": "chisel:bricks2|0",
      "emc": 64
    },
    {
      "item": "chisel:bricks2|1",
      "emc": 64
    },
    {
      "item": "chisel:bricks2|2",
      "emc": 64
    },
    {
      "item": "chisel:bricks2|3",
      "emc": 64
    },
    {
      "item": "chisel:bricks2|4",
      "emc": 64
    },
    {
      "item": "chisel:bricks2|5",
      "emc": 64
    },
    {
      "item": "chisel:blockbronze|0",
      "emc": 1440
    },
    {
      "item": "chisel:blockbronze|1",
      "emc": 1440
    },
    {
      "item": "chisel:blockbronze|2",
      "emc": 1440
    },
    {
      "item": "chisel:blockbronze|3",
      "emc": 1440
    },
    {
      "item": "chisel:blockbronze|4",
      "emc": 1440
    },
    {
      "item": "chisel:blockbronze|5",
      "emc": 1440
    },
    {
      "item": "chisel:blockbronze|6",
      "emc": 1440
    },
    {
      "item": "chisel:brownstone|1",
      "emc": 8
    },
    {
      "item": "chisel:brownstone|2",
      "emc": 8
    },
    {
      "item": "chisel:brownstone|3",
      "emc": 8
    },
    {
      "item": "chisel:brownstone|4",
      "emc": 8
    },
    {
      "item": "chisel:brownstone|5",
      "emc": 8
    },
    {
      "item": "chisel:brownstone|6",
      "emc": 8
    },
    {
      "item": "chisel:brownstone|7",
      "emc": 8
    },
    {
      "item": "chisel:brownstone|8",
      "emc": 8
    },
    {
      "item": "chisel:brownstone|9",
      "emc": 8
    },
    {
      "item": "chisel:certus|0",
      "emc": 256
    },
    {
      "item": "chisel:certus|1",
      "emc": 256
    },
    {
      "item": "chisel:certus|2",
      "emc": 256
    },
    {
      "item": "chisel:certus|3",
      "emc": 256
    },
    {
      "item": "chisel:certus|4",
      "emc": 256
    },
    {
      "item": "chisel:certus|5",
      "emc": 256
    },
    {
      "item": "chisel:certus|6",
      "emc": 256
    },
    {
      "item": "chisel:certus|7",
      "emc": 256
    },
    {
      "item": "chisel:certus|8",
      "emc": 256
    },
    {
      "item": "chisel:certus|9",
      "emc": 256
    },
    {
      "item": "chisel:certus|10",
      "emc": 256
    },
    {
      "item": "chisel:certus|11",
      "emc": 256
    },
    {
      "item": "chisel:certus|12",
      "emc": 256
    },
    {
      "item": "chisel:certus|13",
      "emc": 256
    },
    {
      "item": "chisel:certus|14",
      "emc": 256
    },
    {
      "item": "chisel:certus|15",
      "emc": 256
    },
    {
      "item": "chisel:certus1|0",
      "emc": 256
    },
    {
      "item": "chisel:certus1|1",
      "emc": 256
    },
    {
      "item": "chisel:certus1|2",
      "emc": 256
    },
    {
      "item": "chisel:certus1|3",
      "emc": 256
    },
    {
      "item": "chisel:certus1|4",
      "emc": 256
    },
    {
      "item": "chisel:certus1|5",
      "emc": 256
    },
    {
      "item": "chisel:certus1|6",
      "emc": 256
    },
    {
      "item": "chisel:certus1|7",
      "emc": 256
    },
    {
      "item": "chisel:certus1|8",
      "emc": 256
    },
    {
      "item": "chisel:certus1|9",
      "emc": 256
    },
    {
      "item": "chisel:certus1|10",
      "emc": 256
    },
    {
      "item": "chisel:certus1|11",
      "emc": 256
    },
    {
      "item": "chisel:certus1|12",
      "emc": 256
    },
    {
      "item": "chisel:certus1|13",
      "emc": 256
    },
    {
      "item": "chisel:certus1|14",
      "emc": 256
    },
    {
      "item": "chisel:certus1|15",
      "emc": 256
    },
    {
      "item": "chisel:certus2|0",
      "emc": 256
    },
    {
      "item": "chisel:certus2|1",
      "emc": 256
    },
    {
      "item": "chisel:carpet_black|0",
      "emc": 42
    },
    {
      "item": "chisel:carpet_black|1",
      "emc": 42
    },
    {
      "item": "chisel:carpet_red|0",
      "emc": 42
    },
    {
      "item": "chisel:carpet_red|1",
      "emc": 42
    },
    {
      "item": "chisel:carpet_green|0",
      "emc": 37
    },
    {
      "item": "chisel:carpet_green|1",
      "emc": 37
    },
    {
      "item": "chisel:carpet_brown|0",
      "emc": 42
    },
    {
      "item": "chisel:carpet_brown|1",
      "emc": 42
    },
    {
      "item": "chisel:carpet_blue|0",
      "emc": 42
    },
    {
      "item": "chisel:carpet_blue|1",
      "emc": 42
    },
    {
      "item": "chisel:carpet_purple|0",
      "emc": 42
    },
    {
      "item": "chisel:carpet_purple|1",
      "emc": 42
    },
    {
      "item": "chisel:carpet_cyan|0",
      "emc": 42
    },
    {
      "item": "chisel:carpet_cyan|1",
      "emc": 42
    },
    {
      "item": "chisel:carpet_lightgray|0",
      "emc": 42
    },
    {
      "item": "chisel:carpet_lightgray|1",
      "emc": 42
    },
    {
      "item": "chisel:carpet_gray|0",
      "emc": 42
    },
    {
      "item": "chisel:carpet_gray|1",
      "emc": 42
    },
    {
      "item": "chisel:carpet_pink|0",
      "emc": 42
    },
    {
      "item": "chisel:carpet_pink|1",
      "emc": 42
    },
    {
      "item": "chisel:carpet_lime|0",
      "emc": 42
    },
    {
      "item": "chisel:carpet_lime|1",
      "emc": 42
    },
    {
      "item": "chisel:carpet_yellow|0",
      "emc": 42
    },
    {
      "item": "chisel:carpet_yellow|1",
      "emc": 42
    },
    {
      "item": "chisel:carpet_lightblue|0",
      "emc": 42
    },
    {
      "item": "chisel:carpet_lightblue|1",
      "emc": 42
    },
    {
      "item": "chisel:carpet_magenta|0",
      "emc": 42
    },
    {
      "item": "chisel:carpet_magenta|1",
      "emc": 42
    },
    {
      "item": "chisel:carpet_orange|0",
      "emc": 42
    },
    {
      "item": "chisel:carpet_orange|1",
      "emc": 42
    },
    {
      "item": "chisel:carpet_white|0",
      "emc": 32
    },
    {
      "item": "chisel:carpet_white|1",
      "emc": 32
    },
    {
      "item": "chisel:block_charcoal|0",
      "emc": 288
    },
    {
      "item": "chisel:block_charcoal|1",
      "emc": 288
    },
    {
      "item": "chisel:block_charcoal|2",
      "emc": 288
    },
    {
      "item": "chisel:block_charcoal|3",
      "emc": 288
    },
    {
      "item": "chisel:block_charcoal|4",
      "emc": 288
    },
    {
      "item": "chisel:block_charcoal|5",
      "emc": 288
    },
    {
      "item": "chisel:block_charcoal|6",
      "emc": 288
    },
    {
      "item": "chisel:block_charcoal|7",
      "emc": 288
    },
    {
      "item": "chisel:block_charcoal|8",
      "emc": 288
    },
    {
      "item": "chisel:block_charcoal|9",
      "emc": 1152
    },
    {
      "item": "chisel:block_charcoal|10",
      "emc": 1152
    },
    {
      "item": "chisel:block_charcoal|11",
      "emc": 1152
    },
    {
      "item": "chisel:block_charcoal|12",
      "emc": 1152
    },
    {
      "item": "chisel:block_charcoal|13",
      "emc": 1152
    },
    {
      "item": "chisel:block_charcoal|14",
      "emc": 1152
    },
    {
      "item": "chisel:block_charcoal|15",
      "emc": 1152
    },
    {
      "item": "chisel:block_charcoal1|0",
      "emc": 1152
    },
    {
      "item": "chisel:block_charcoal1|1",
      "emc": 1152
    },
    {
      "item": "chisel:block_charcoal1|2",
      "emc": 1152
    },
    {
      "item": "chisel:block_charcoal1|3",
      "emc": 1152
    },
    {
      "item": "chisel:block_charcoal1|4",
      "emc": 1152
    },
    {
      "item": "chisel:block_charcoal1|5",
      "emc": 1152
    },
    {
      "item": "chisel:block_charcoal1|6",
      "emc": 1152
    },
    {
      "item": "chisel:block_charcoal1|7",
      "emc": 1152
    },
    {
      "item": "chisel:block_charcoal1|8",
      "emc": 1152
    },
    {
      "item": "chisel:block_charcoal1|9",
      "emc": 1152
    },
    {
      "item": "chisel:block_charcoal1|10",
      "emc": 1152
    },
    {
      "item": "chisel:block_charcoal1|11",
      "emc": 288
    },
    {
      "item": "chisel:block_charcoal1|12",
      "emc": 288
    },
    {
      "item": "chisel:block_charcoal1|13",
      "emc": 288
    },
    {
      "item": "chisel:block_charcoal1|14",
      "emc": 288
    },
    {
      "item": "chisel:block_charcoal1|15",
      "emc": 288
    },
    {
      "item": "chisel:block_charcoal2|0",
      "emc": 288
    },
    {
      "item": "chisel:block_charcoal2|1",
      "emc": 288
    },
    {
      "item": "chisel:cloud|1",
      "emc": 6
    },
    {
      "item": "chisel:cloud|2",
      "emc": 6
    },
    {
      "item": "chisel:cloud|3",
      "emc": 6
    },
    {
      "item": "chisel:cloud|4",
      "emc": 6
    },
    {
      "item": "chisel:blockcobalt|3",
      "emc": 9216
    },
    {
      "item": "chisel:blockcobalt|0",
      "emc": 9216
    },
    {
      "item": "chisel:blockcobalt|1",
      "emc": 9216
    },
    {
      "item": "chisel:blockcobalt|2",
      "emc": 9216
    },
    {
      "item": "chisel:blockcobalt|4",
      "emc": 9216
    },
    {
      "item": "chisel:blockcobalt|5",
      "emc": 9216
    },
    {
      "item": "chisel:blockcobalt|6",
      "emc": 9216
    },
    {
      "item": "chisel:block_coal|0",
      "emc": 1152
    },
    {
      "item": "chisel:block_coal|1",
      "emc": 1152
    },
    {
      "item": "chisel:block_coal|2",
      "emc": 1152
    },
    {
      "item": "chisel:block_coal|3",
      "emc": 1152
    },
    {
      "item": "chisel:block_coal|4",
      "emc": 1152
    },
    {
      "item": "chisel:block_coal|5",
      "emc": 1152
    },
    {
      "item": "chisel:block_coal|6",
      "emc": 1152
    },
    {
      "item": "chisel:block_coal|7",
      "emc": 1152
    },
    {
      "item": "chisel:block_coal|8",
      "emc": 1152
    },
    {
      "item": "chisel:block_coal|9",
      "emc": 1152
    },
    {
      "item": "chisel:block_coal|10",
      "emc": 1152
    },
    {
      "item": "chisel:block_coal|11",
      "emc": 1152
    },
    {
      "item": "chisel:block_coal|12",
      "emc": 1152
    },
    {
      "item": "chisel:block_coal|13",
      "emc": 1152
    },
    {
      "item": "chisel:block_coal|14",
      "emc": 1152
    },
    {
      "item": "chisel:block_coal|15",
      "emc": 1152
    },
    {
      "item": "chisel:block_coal1|0",
      "emc": 1152
    },
    {
      "item": "chisel:block_coal1|1",
      "emc": 1152
    },
    {
      "item": "chisel:block_coal1|2",
      "emc": 1152
    },
    {
      "item": "chisel:block_coal1|3",
      "emc": 1152
    },
    {
      "item": "chisel:block_coal1|4",
      "emc": 1152
    },
    {
      "item": "chisel:block_coal1|5",
      "emc": 1152
    },
    {
      "item": "chisel:block_coal1|6",
      "emc": 1152
    },
    {
      "item": "chisel:block_coal1|7",
      "emc": 1152
    },
    {
      "item": "chisel:block_coal1|8",
      "emc": 1152
    },
    {
      "item": "chisel:block_coal1|9",
      "emc": 1152
    },
    {
      "item": "chisel:block_coal1|10",
      "emc": 1152
    },
    {
      "item": "chisel:block_coal1|11",
      "emc": 1152
    },
    {
      "item": "chisel:block_coal1|12",
      "emc": 1152
    },
    {
      "item": "chisel:block_coal1|13",
      "emc": 1152
    },
    {
      "item": "chisel:block_coal1|14",
      "emc": 1152
    },
    {
      "item": "chisel:block_coal1|15",
      "emc": 1152
    },
    {
      "item": "chisel:block_coal2|0",
      "emc": 1152
    },
    {
      "item": "chisel:block_coal2|1",
      "emc": 1152
    },
    {
      "item": "chisel:cobblestonemossy|0",
      "emc": 9
    },
    {
      "item": "chisel:cobblestonemossy|1",
      "emc": 9
    },
    {
      "item": "chisel:cobblestonemossy|2",
      "emc": 9
    },
    {
      "item": "chisel:cobblestonemossy|3",
      "emc": 9
    },
    {
      "item": "chisel:cobblestonemossy|4",
      "emc": 9
    },
    {
      "item": "chisel:cobblestonemossy|5",
      "emc": 9
    },
    {
      "item": "chisel:cobblestonemossy|6",
      "emc": 9
    },
    {
      "item": "chisel:cobblestonemossy|7",
      "emc": 9
    },
    {
      "item": "chisel:cobblestonemossy|8",
      "emc": 9
    },
    {
      "item": "chisel:cobblestonemossy|9",
      "emc": 9
    },
    {
      "item": "chisel:cobblestonemossy|10",
      "emc": 9
    },
    {
      "item": "chisel:cobblestonemossy|11",
      "emc": 9
    },
    {
      "item": "chisel:cobblestonemossy|12",
      "emc": 9
    },
    {
      "item": "chisel:cobblestonemossy|13",
      "emc": 9
    },
    {
      "item": "chisel:cobblestonemossy|14",
      "emc": 9
    },
    {
      "item": "chisel:cobblestonemossy|15",
      "emc": 9
    },
    {
      "item": "chisel:cobblestonemossy1|0",
      "emc": 9
    },
    {
      "item": "chisel:cobblestonemossy1|1",
      "emc": 9
    },
    {
      "item": "chisel:cobblestonemossy1|2",
      "emc": 9
    },
    {
      "item": "chisel:cobblestonemossy1|3",
      "emc": 9
    },
    {
      "item": "chisel:cobblestonemossy1|4",
      "emc": 9
    },
    {
      "item": "chisel:cobblestonemossy1|5",
      "emc": 9
    },
    {
      "item": "chisel:cobblestonemossy1|6",
      "emc": 9
    },
    {
      "item": "chisel:cobblestonemossy1|7",
      "emc": 9
    },
    {
      "item": "chisel:cobblestonemossy1|8",
      "emc": 9
    },
    {
      "item": "chisel:cobblestonemossy1|9",
      "emc": 9
    },
    {
      "item": "chisel:cobblestonemossy1|10",
      "emc": 9
    },
    {
      "item": "chisel:cobblestonemossy2|0",
      "emc": 9
    },
    {
      "item": "chisel:cobblestonemossy1|11",
      "emc": 9
    },
    {
      "item": "chisel:cobblestonemossy1|12",
      "emc": 9
    },
    {
      "item": "chisel:cobblestonemossy1|13",
      "emc": 9
    },
    {
      "item": "chisel:cobblestonemossy1|14",
      "emc": 9
    },
    {
      "item": "chisel:cobblestonemossy1|15",
      "emc": 9
    },
    {
      "item": "chisel:concrete_black|0",
      "emc": 4
    },
    {
      "item": "chisel:concrete_black|1",
      "emc": 4
    },
    {
      "item": "chisel:concrete_black|2",
      "emc": 4
    },
    {
      "item": "chisel:concrete_black|3",
      "emc": 4
    },
    {
      "item": "chisel:concrete_black|4",
      "emc": 4
    },
    {
      "item": "chisel:concrete_black|5",
      "emc": 4
    },
    {
      "item": "chisel:concrete_black|6",
      "emc": 4
    },
    {
      "item": "chisel:concrete_black|7",
      "emc": 4
    },
    {
      "item": "chisel:concrete_black|8",
      "emc": 4
    },
    {
      "item": "chisel:concrete_black|9",
      "emc": 4
    },
    {
      "item": "chisel:concrete_black|10",
      "emc": 4
    },
    {
      "item": "chisel:concrete_black|11",
      "emc": 4
    },
    {
      "item": "chisel:concrete_black|12",
      "emc": 4
    },
    {
      "item": "chisel:concrete_black|13",
      "emc": 4
    },
    {
      "item": "chisel:concrete_black|14",
      "emc": 4
    },
    {
      "item": "chisel:concrete_black|15",
      "emc": 4
    },
    {
      "item": "chisel:concrete_black1|0",
      "emc": 4
    },
    {
      "item": "chisel:concrete_black1|1",
      "emc": 4
    },
    {
      "item": "chisel:concrete_black1|2",
      "emc": 4
    },
    {
      "item": "chisel:concrete_black1|3",
      "emc": 4
    },
    {
      "item": "chisel:concrete_black1|4",
      "emc": 4
    },
    {
      "item": "chisel:concrete_black1|5",
      "emc": 4
    },
    {
      "item": "chisel:concrete_black1|6",
      "emc": 4
    },
    {
      "item": "chisel:concrete_black1|7",
      "emc": 4
    },
    {
      "item": "chisel:concrete_black1|8",
      "emc": 4
    },
    {
      "item": "chisel:concrete_black1|9",
      "emc": 4
    },
    {
      "item": "chisel:concrete_black1|10",
      "emc": 4
    },
    {
      "item": "chisel:concrete_black1|11",
      "emc": 4
    },
    {
      "item": "chisel:concrete_black1|12",
      "emc": 4
    },
    {
      "item": "chisel:concrete_black1|13",
      "emc": 4
    },
    {
      "item": "chisel:concrete_black1|14",
      "emc": 4
    },
    {
      "item": "chisel:concrete_black1|15",
      "emc": 4
    },
    {
      "item": "chisel:concrete_black2|0",
      "emc": 4
    },
    {
      "item": "chisel:concrete_red|0",
      "emc": 4
    },
    {
      "item": "chisel:concrete_red|1",
      "emc": 4
    },
    {
      "item": "chisel:concrete_red|2",
      "emc": 4
    },
    {
      "item": "chisel:concrete_red|3",
      "emc": 4
    },
    {
      "item": "chisel:concrete_red|4",
      "emc": 4
    },
    {
      "item": "chisel:concrete_red|5",
      "emc": 4
    },
    {
      "item": "chisel:concrete_red|6",
      "emc": 4
    },
    {
      "item": "chisel:concrete_red|7",
      "emc": 4
    },
    {
      "item": "chisel:concrete_red|8",
      "emc": 4
    },
    {
      "item": "chisel:concrete_red|9",
      "emc": 4
    },
    {
      "item": "chisel:concrete_red|10",
      "emc": 4
    },
    {
      "item": "chisel:concrete_red|11",
      "emc": 4
    },
    {
      "item": "chisel:concrete_red|12",
      "emc": 4
    },
    {
      "item": "chisel:concrete_red|13",
      "emc": 4
    },
    {
      "item": "chisel:concrete_red|14",
      "emc": 4
    },
    {
      "item": "chisel:concrete_red|15",
      "emc": 4
    },
    {
      "item": "chisel:concrete_red1|0",
      "emc": 4
    },
    {
      "item": "chisel:concrete_red1|1",
      "emc": 4
    },
    {
      "item": "chisel:concrete_red1|2",
      "emc": 4
    },
    {
      "item": "chisel:concrete_red1|3",
      "emc": 4
    },
    {
      "item": "chisel:concrete_red1|4",
      "emc": 4
    },
    {
      "item": "chisel:concrete_red1|5",
      "emc": 4
    },
    {
      "item": "chisel:concrete_red1|6",
      "emc": 4
    },
    {
      "item": "chisel:concrete_red1|7",
      "emc": 4
    },
    {
      "item": "chisel:concrete_red1|8",
      "emc": 4
    },
    {
      "item": "chisel:concrete_red1|9",
      "emc": 4
    },
    {
      "item": "chisel:concrete_red1|10",
      "emc": 4
    },
    {
      "item": "chisel:concrete_red1|11",
      "emc": 4
    },
    {
      "item": "chisel:concrete_red1|12",
      "emc": 4
    },
    {
      "item": "chisel:concrete_red1|13",
      "emc": 4
    },
    {
      "item": "chisel:concrete_red1|14",
      "emc": 4
    },
    {
      "item": "chisel:concrete_red1|15",
      "emc": 4
    },
    {
      "item": "chisel:concrete_red2|0",
      "emc": 4
    },
    {
      "item": "chisel:concrete_green|0",
      "emc": 3
    },
    {
      "item": "chisel:concrete_green|1",
      "emc": 3
    },
    {
      "item": "chisel:concrete_green|2",
      "emc": 3
    },
    {
      "item": "chisel:concrete_green|3",
      "emc": 3
    },
    {
      "item": "chisel:concrete_green|4",
      "emc": 3
    },
    {
      "item": "chisel:concrete_green|5",
      "emc": 3
    },
    {
      "item": "chisel:concrete_green|6",
      "emc": 3
    },
    {
      "item": "chisel:concrete_green|7",
      "emc": 3
    },
    {
      "item": "chisel:concrete_green|8",
      "emc": 3
    },
    {
      "item": "chisel:concrete_green|9",
      "emc": 3
    },
    {
      "item": "chisel:concrete_green|10",
      "emc": 3
    },
    {
      "item": "chisel:concrete_green|11",
      "emc": 3
    },
    {
      "item": "chisel:concrete_green|12",
      "emc": 3
    },
    {
      "item": "chisel:concrete_green|13",
      "emc": 3
    },
    {
      "item": "chisel:concrete_green|14",
      "emc": 3
    },
    {
      "item": "chisel:concrete_green|15",
      "emc": 3
    },
    {
      "item": "chisel:concrete_green1|0",
      "emc": 3
    },
    {
      "item": "chisel:concrete_green1|1",
      "emc": 3
    },
    {
      "item": "chisel:concrete_green1|2",
      "emc": 3
    },
    {
      "item": "chisel:concrete_green1|3",
      "emc": 3
    },
    {
      "item": "chisel:concrete_green1|4",
      "emc": 3
    },
    {
      "item": "chisel:concrete_green1|5",
      "emc": 3
    },
    {
      "item": "chisel:concrete_green1|6",
      "emc": 3
    },
    {
      "item": "chisel:concrete_green1|7",
      "emc": 3
    },
    {
      "item": "chisel:concrete_green1|8",
      "emc": 3
    },
    {
      "item": "chisel:concrete_green1|9",
      "emc": 3
    },
    {
      "item": "chisel:concrete_green1|10",
      "emc": 3
    },
    {
      "item": "chisel:concrete_green1|11",
      "emc": 3
    },
    {
      "item": "chisel:concrete_green1|12",
      "emc": 3
    },
    {
      "item": "chisel:concrete_green1|13",
      "emc": 3
    },
    {
      "item": "chisel:concrete_green1|14",
      "emc": 3
    },
    {
      "item": "chisel:concrete_green1|15",
      "emc": 3
    },
    {
      "item": "chisel:concrete_green2|0",
      "emc": 3
    },
    {
      "item": "chisel:concrete_brown|0",
      "emc": 4
    },
    {
      "item": "chisel:concrete_brown|1",
      "emc": 4
    },
    {
      "item": "chisel:concrete_brown|2",
      "emc": 4
    },
    {
      "item": "chisel:concrete_brown|3",
      "emc": 4
    },
    {
      "item": "chisel:concrete_brown|4",
      "emc": 4
    },
    {
      "item": "chisel:concrete_brown|5",
      "emc": 4
    },
    {
      "item": "chisel:concrete_brown|6",
      "emc": 4
    },
    {
      "item": "chisel:concrete_brown|7",
      "emc": 4
    },
    {
      "item": "chisel:concrete_brown|8",
      "emc": 4
    },
    {
      "item": "chisel:concrete_brown|11",
      "emc": 4
    },
    {
      "item": "chisel:concrete_brown|12",
      "emc": 4
    },
    {
      "item": "chisel:concrete_brown|13",
      "emc": 4
    },
    {
      "item": "chisel:concrete_brown|14",
      "emc": 4
    },
    {
      "item": "chisel:concrete_brown|15",
      "emc": 4
    },
    {
      "item": "chisel:concrete_brown1|0",
      "emc": 4
    },
    {
      "item": "chisel:concrete_brown1|1",
      "emc": 4
    },
    {
      "item": "chisel:concrete_brown1|2",
      "emc": 4
    },
    {
      "item": "chisel:concrete_brown1|3",
      "emc": 4
    },
    {
      "item": "chisel:concrete_brown|9",
      "emc": 4
    },
    {
      "item": "chisel:concrete_brown|10",
      "emc": 4
    },
    {
      "item": "chisel:concrete_brown1|4",
      "emc": 4
    },
    {
      "item": "chisel:concrete_brown1|5",
      "emc": 4
    },
    {
      "item": "chisel:concrete_brown1|6",
      "emc": 4
    },
    {
      "item": "chisel:concrete_brown1|7",
      "emc": 4
    },
    {
      "item": "chisel:concrete_brown1|8",
      "emc": 4
    },
    {
      "item": "chisel:concrete_brown1|9",
      "emc": 4
    },
    {
      "item": "chisel:concrete_brown1|10",
      "emc": 4
    },
    {
      "item": "chisel:concrete_brown1|11",
      "emc": 4
    },
    {
      "item": "chisel:concrete_brown1|12",
      "emc": 4
    },
    {
      "item": "chisel:concrete_brown1|13",
      "emc": 4
    },
    {
      "item": "chisel:concrete_brown1|14",
      "emc": 4
    },
    {
      "item": "chisel:concrete_brown1|15",
      "emc": 4
    },
    {
      "item": "chisel:concrete_brown2|0",
      "emc": 4
    },
    {
      "item": "chisel:concrete_blue|0",
      "emc": 4
    },
    {
      "item": "chisel:concrete_blue|1",
      "emc": 4
    },
    {
      "item": "chisel:concrete_blue|2",
      "emc": 4
    },
    {
      "item": "chisel:concrete_blue|3",
      "emc": 4
    },
    {
      "item": "chisel:concrete_blue|4",
      "emc": 4
    },
    {
      "item": "chisel:concrete_blue|5",
      "emc": 4
    },
    {
      "item": "chisel:concrete_blue|6",
      "emc": 4
    },
    {
      "item": "chisel:concrete_blue|7",
      "emc": 4
    },
    {
      "item": "chisel:concrete_blue|8",
      "emc": 4
    },
    {
      "item": "chisel:concrete_blue|9",
      "emc": 4
    },
    {
      "item": "chisel:concrete_blue|10",
      "emc": 4
    },
    {
      "item": "chisel:concrete_blue|11",
      "emc": 4
    },
    {
      "item": "chisel:concrete_blue|12",
      "emc": 4
    },
    {
      "item": "chisel:concrete_blue|13",
      "emc": 4
    },
    {
      "item": "chisel:concrete_blue|14",
      "emc": 4
    },
    {
      "item": "chisel:concrete_blue|15",
      "emc": 4
    },
    {
      "item": "chisel:concrete_blue1|0",
      "emc": 4
    },
    {
      "item": "chisel:concrete_blue1|1",
      "emc": 4
    },
    {
      "item": "chisel:concrete_blue1|2",
      "emc": 4
    },
    {
      "item": "chisel:concrete_blue1|3",
      "emc": 4
    },
    {
      "item": "chisel:concrete_blue1|4",
      "emc": 4
    },
    {
      "item": "chisel:concrete_blue1|5",
      "emc": 4
    },
    {
      "item": "chisel:concrete_blue1|6",
      "emc": 4
    },
    {
      "item": "chisel:concrete_blue1|7",
      "emc": 4
    },
    {
      "item": "chisel:concrete_blue1|8",
      "emc": 4
    },
    {
      "item": "chisel:concrete_blue1|9",
      "emc": 4
    },
    {
      "item": "chisel:concrete_blue1|10",
      "emc": 4
    },
    {
      "item": "chisel:concrete_blue1|11",
      "emc": 4
    },
    {
      "item": "chisel:concrete_blue1|12",
      "emc": 4
    },
    {
      "item": "chisel:concrete_blue1|13",
      "emc": 4
    },
    {
      "item": "chisel:concrete_blue1|14",
      "emc": 4
    },
    {
      "item": "chisel:concrete_blue1|15",
      "emc": 4
    },
    {
      "item": "chisel:concrete_blue2|0",
      "emc": 4
    },
    {
      "item": "chisel:concrete_purple|0",
      "emc": 4
    },
    {
      "item": "chisel:concrete_purple|1",
      "emc": 4
    },
    {
      "item": "chisel:concrete_purple|2",
      "emc": 4
    },
    {
      "item": "chisel:concrete_purple|3",
      "emc": 4
    },
    {
      "item": "chisel:concrete_purple|4",
      "emc": 4
    },
    {
      "item": "chisel:concrete_purple|5",
      "emc": 4
    },
    {
      "item": "chisel:concrete_purple|6",
      "emc": 4
    },
    {
      "item": "chisel:concrete_purple|7",
      "emc": 4
    },
    {
      "item": "chisel:concrete_purple|8",
      "emc": 4
    },
    {
      "item": "chisel:concrete_purple|9",
      "emc": 4
    },
    {
      "item": "chisel:concrete_purple|10",
      "emc": 4
    },
    {
      "item": "chisel:concrete_purple|11",
      "emc": 4
    },
    {
      "item": "chisel:concrete_purple|12",
      "emc": 4
    },
    {
      "item": "chisel:concrete_purple|13",
      "emc": 4
    },
    {
      "item": "chisel:concrete_purple|14",
      "emc": 4
    },
    {
      "item": "chisel:concrete_purple|15",
      "emc": 4
    },
    {
      "item": "chisel:concrete_purple1|0",
      "emc": 4
    },
    {
      "item": "chisel:concrete_purple1|1",
      "emc": 4
    },
    {
      "item": "chisel:concrete_purple1|2",
      "emc": 4
    },
    {
      "item": "chisel:concrete_purple1|3",
      "emc": 4
    },
    {
      "item": "chisel:concrete_purple1|4",
      "emc": 4
    },
    {
      "item": "chisel:concrete_purple1|5",
      "emc": 4
    },
    {
      "item": "chisel:concrete_purple1|6",
      "emc": 4
    },
    {
      "item": "chisel:concrete_purple1|7",
      "emc": 4
    },
    {
      "item": "chisel:concrete_purple1|8",
      "emc": 4
    },
    {
      "item": "chisel:concrete_purple1|9",
      "emc": 4
    },
    {
      "item": "chisel:concrete_purple1|10",
      "emc": 4
    },
    {
      "item": "chisel:concrete_purple1|11",
      "emc": 4
    },
    {
      "item": "chisel:concrete_purple1|12",
      "emc": 4
    },
    {
      "item": "chisel:concrete_purple1|13",
      "emc": 4
    },
    {
      "item": "chisel:concrete_purple1|14",
      "emc": 4
    },
    {
      "item": "chisel:concrete_purple1|15",
      "emc": 4
    },
    {
      "item": "chisel:concrete_purple2|0",
      "emc": 4
    },
    {
      "item": "chisel:concrete_cyan|0",
      "emc": 4
    },
    {
      "item": "chisel:concrete_cyan|1",
      "emc": 4
    },
    {
      "item": "chisel:concrete_cyan|2",
      "emc": 4
    },
    {
      "item": "chisel:concrete_cyan|3",
      "emc": 4
    },
    {
      "item": "chisel:concrete_cyan|4",
      "emc": 4
    },
    {
      "item": "chisel:concrete_cyan|5",
      "emc": 4
    },
    {
      "item": "chisel:concrete_cyan|6",
      "emc": 4
    },
    {
      "item": "chisel:concrete_cyan|7",
      "emc": 4
    },
    {
      "item": "chisel:concrete_cyan|8",
      "emc": 4
    },
    {
      "item": "chisel:concrete_cyan|9",
      "emc": 4
    },
    {
      "item": "chisel:concrete_cyan|10",
      "emc": 4
    },
    {
      "item": "chisel:concrete_cyan|11",
      "emc": 4
    },
    {
      "item": "chisel:concrete_cyan|12",
      "emc": 4
    },
    {
      "item": "chisel:concrete_cyan|13",
      "emc": 4
    },
    {
      "item": "chisel:concrete_cyan|14",
      "emc": 4
    },
    {
      "item": "chisel:concrete_cyan|15",
      "emc": 4
    },
    {
      "item": "chisel:concrete_cyan1|0",
      "emc": 4
    },
    {
      "item": "chisel:concrete_cyan1|1",
      "emc": 4
    },
    {
      "item": "chisel:concrete_cyan1|2",
      "emc": 4
    },
    {
      "item": "chisel:concrete_cyan1|3",
      "emc": 4
    },
    {
      "item": "chisel:concrete_cyan1|4",
      "emc": 4
    },
    {
      "item": "chisel:concrete_cyan1|5",
      "emc": 4
    },
    {
      "item": "chisel:concrete_cyan1|6",
      "emc": 4
    },
    {
      "item": "chisel:concrete_cyan1|7",
      "emc": 4
    },
    {
      "item": "chisel:concrete_cyan1|8",
      "emc": 4
    },
    {
      "item": "chisel:concrete_cyan1|9",
      "emc": 4
    },
    {
      "item": "chisel:concrete_cyan1|10",
      "emc": 4
    },
    {
      "item": "chisel:concrete_cyan1|11",
      "emc": 4
    },
    {
      "item": "chisel:concrete_cyan1|12",
      "emc": 4
    },
    {
      "item": "chisel:concrete_cyan1|13",
      "emc": 4
    },
    {
      "item": "chisel:concrete_cyan1|14",
      "emc": 4
    },
    {
      "item": "chisel:concrete_cyan1|15",
      "emc": 4
    },
    {
      "item": "chisel:concrete_cyan2|0",
      "emc": 4
    },
    {
      "item": "chisel:concrete_lightgray|0",
      "emc": 4
    },
    {
      "item": "chisel:concrete_lightgray|1",
      "emc": 4
    },
    {
      "item": "chisel:concrete_lightgray|2",
      "emc": 4
    },
    {
      "item": "chisel:concrete_lightgray|3",
      "emc": 4
    },
    {
      "item": "chisel:concrete_lightgray|4",
      "emc": 4
    },
    {
      "item": "chisel:concrete_lightgray|5",
      "emc": 4
    },
    {
      "item": "chisel:concrete_lightgray|6",
      "emc": 4
    },
    {
      "item": "chisel:concrete_lightgray|7",
      "emc": 4
    },
    {
      "item": "chisel:concrete_lightgray|8",
      "emc": 4
    },
    {
      "item": "chisel:concrete_lightgray|9",
      "emc": 4
    },
    {
      "item": "chisel:concrete_lightgray|10",
      "emc": 4
    },
    {
      "item": "chisel:concrete_lightgray|11",
      "emc": 4
    },
    {
      "item": "chisel:concrete_lightgray|12",
      "emc": 4
    },
    {
      "item": "chisel:concrete_lightgray|13",
      "emc": 4
    },
    {
      "item": "chisel:concrete_lightgray|14",
      "emc": 4
    },
    {
      "item": "chisel:concrete_lightgray|15",
      "emc": 4
    },
    {
      "item": "chisel:concrete_lightgray1|0",
      "emc": 4
    },
    {
      "item": "chisel:concrete_lightgray1|1",
      "emc": 4
    },
    {
      "item": "chisel:concrete_lightgray1|2",
      "emc": 4
    },
    {
      "item": "chisel:concrete_lightgray1|3",
      "emc": 4
    },
    {
      "item": "chisel:concrete_lightgray1|4",
      "emc": 4
    },
    {
      "item": "chisel:concrete_lightgray1|5",
      "emc": 4
    },
    {
      "item": "chisel:concrete_lightgray1|6",
      "emc": 4
    },
    {
      "item": "chisel:concrete_lightgray1|7",
      "emc": 4
    },
    {
      "item": "chisel:concrete_lightgray1|8",
      "emc": 4
    },
    {
      "item": "chisel:concrete_lightgray1|9",
      "emc": 4
    },
    {
      "item": "chisel:concrete_lightgray1|10",
      "emc": 4
    },
    {
      "item": "chisel:concrete_lightgray1|11",
      "emc": 4
    },
    {
      "item": "chisel:concrete_lightgray1|12",
      "emc": 4
    },
    {
      "item": "chisel:concrete_lightgray1|13",
      "emc": 4
    },
    {
      "item": "chisel:concrete_lightgray1|14",
      "emc": 4
    },
    {
      "item": "chisel:concrete_lightgray1|15",
      "emc": 4
    },
    {
      "item": "chisel:concrete_lightgray2|0",
      "emc": 4
    },
    {
      "item": "chisel:concrete_gray|0",
      "emc": 4
    },
    {
      "item": "chisel:concrete_gray|1",
      "emc": 4
    },
    {
      "item": "chisel:concrete_gray|2",
      "emc": 4
    },
    {
      "item": "chisel:concrete_gray|3",
      "emc": 4
    },
    {
      "item": "chisel:concrete_gray|4",
      "emc": 4
    },
    {
      "item": "chisel:concrete_gray|5",
      "emc": 4
    },
    {
      "item": "chisel:concrete_gray|6",
      "emc": 4
    },
    {
      "item": "chisel:concrete_gray|7",
      "emc": 4
    },
    {
      "item": "chisel:concrete_gray|8",
      "emc": 4
    },
    {
      "item": "chisel:concrete_gray|9",
      "emc": 4
    },
    {
      "item": "chisel:concrete_gray|10",
      "emc": 4
    },
    {
      "item": "chisel:concrete_gray|11",
      "emc": 4
    },
    {
      "item": "chisel:concrete_gray|12",
      "emc": 4
    },
    {
      "item": "chisel:concrete_gray|13",
      "emc": 4
    },
    {
      "item": "chisel:concrete_gray|14",
      "emc": 4
    },
    {
      "item": "chisel:concrete_gray|15",
      "emc": 4
    },
    {
      "item": "chisel:concrete_gray1|0",
      "emc": 4
    },
    {
      "item": "chisel:concrete_gray1|1",
      "emc": 4
    },
    {
      "item": "chisel:concrete_gray1|2",
      "emc": 4
    },
    {
      "item": "chisel:concrete_gray1|3",
      "emc": 4
    },
    {
      "item": "chisel:concrete_gray1|4",
      "emc": 4
    },
    {
      "item": "chisel:concrete_gray1|5",
      "emc": 4
    },
    {
      "item": "chisel:concrete_gray1|6",
      "emc": 4
    },
    {
      "item": "chisel:concrete_gray1|7",
      "emc": 4
    },
    {
      "item": "chisel:concrete_gray1|8",
      "emc": 4
    },
    {
      "item": "chisel:concrete_gray1|9",
      "emc": 4
    },
    {
      "item": "chisel:concrete_gray1|10",
      "emc": 4
    },
    {
      "item": "chisel:concrete_gray1|11",
      "emc": 4
    },
    {
      "item": "chisel:concrete_gray1|12",
      "emc": 4
    },
    {
      "item": "chisel:concrete_gray1|13",
      "emc": 4
    },
    {
      "item": "chisel:concrete_gray1|14",
      "emc": 4
    },
    {
      "item": "chisel:concrete_gray1|15",
      "emc": 4
    },
    {
      "item": "chisel:concrete_gray2|0",
      "emc": 4
    },
    {
      "item": "chisel:concrete_pink|0",
      "emc": 4
    },
    {
      "item": "chisel:concrete_pink|1",
      "emc": 4
    },
    {
      "item": "chisel:concrete_pink|2",
      "emc": 4
    },
    {
      "item": "chisel:concrete_pink|3",
      "emc": 4
    },
    {
      "item": "chisel:concrete_pink|4",
      "emc": 4
    },
    {
      "item": "chisel:concrete_pink|5",
      "emc": 4
    },
    {
      "item": "chisel:concrete_pink|6",
      "emc": 4
    },
    {
      "item": "chisel:concrete_pink|7",
      "emc": 4
    },
    {
      "item": "chisel:concrete_pink|8",
      "emc": 4
    },
    {
      "item": "chisel:concrete_pink|9",
      "emc": 4
    },
    {
      "item": "chisel:concrete_pink|10",
      "emc": 4
    },
    {
      "item": "chisel:concrete_pink|11",
      "emc": 4
    },
    {
      "item": "chisel:concrete_pink|12",
      "emc": 4
    },
    {
      "item": "chisel:concrete_pink|13",
      "emc": 4
    },
    {
      "item": "chisel:concrete_pink|14",
      "emc": 4
    },
    {
      "item": "chisel:concrete_pink|15",
      "emc": 4
    },
    {
      "item": "chisel:concrete_pink1|0",
      "emc": 4
    },
    {
      "item": "chisel:concrete_pink1|1",
      "emc": 4
    },
    {
      "item": "chisel:concrete_pink1|2",
      "emc": 4
    },
    {
      "item": "chisel:concrete_pink1|3",
      "emc": 4
    },
    {
      "item": "chisel:concrete_pink1|4",
      "emc": 4
    },
    {
      "item": "chisel:concrete_pink1|5",
      "emc": 4
    },
    {
      "item": "chisel:concrete_pink1|6",
      "emc": 4
    },
    {
      "item": "chisel:concrete_pink1|7",
      "emc": 4
    },
    {
      "item": "chisel:concrete_pink1|8",
      "emc": 4
    },
    {
      "item": "chisel:concrete_pink1|9",
      "emc": 4
    },
    {
      "item": "chisel:concrete_pink1|10",
      "emc": 4
    },
    {
      "item": "chisel:concrete_pink1|11",
      "emc": 4
    },
    {
      "item": "chisel:concrete_pink1|12",
      "emc": 4
    },
    {
      "item": "chisel:concrete_pink1|13",
      "emc": 4
    },
    {
      "item": "chisel:concrete_pink1|14",
      "emc": 4
    },
    {
      "item": "chisel:concrete_pink1|15",
      "emc": 4
    },
    {
      "item": "chisel:concrete_pink2|0",
      "emc": 4
    },
    {
      "item": "chisel:concrete_lime|0",
      "emc": 4
    },
    {
      "item": "chisel:concrete_lime|1",
      "emc": 4
    },
    {
      "item": "chisel:concrete_lime|2",
      "emc": 4
    },
    {
      "item": "chisel:concrete_lime|3",
      "emc": 4
    },
    {
      "item": "chisel:concrete_lime|4",
      "emc": 4
    },
    {
      "item": "chisel:concrete_lime|5",
      "emc": 4
    },
    {
      "item": "chisel:concrete_lime|6",
      "emc": 4
    },
    {
      "item": "chisel:concrete_lime|7",
      "emc": 4
    },
    {
      "item": "chisel:concrete_lime|8",
      "emc": 4
    },
    {
      "item": "chisel:concrete_lime|9",
      "emc": 4
    },
    {
      "item": "chisel:concrete_lime|10",
      "emc": 4
    },
    {
      "item": "chisel:concrete_lime|11",
      "emc": 4
    },
    {
      "item": "chisel:concrete_lime|12",
      "emc": 4
    },
    {
      "item": "chisel:concrete_lime|13",
      "emc": 4
    },
    {
      "item": "chisel:concrete_lime|14",
      "emc": 4
    },
    {
      "item": "chisel:concrete_lime|15",
      "emc": 4
    },
    {
      "item": "chisel:concrete_lime1|0",
      "emc": 4
    },
    {
      "item": "chisel:concrete_lime1|1",
      "emc": 4
    },
    {
      "item": "chisel:concrete_lime1|2",
      "emc": 4
    },
    {
      "item": "chisel:concrete_lime1|3",
      "emc": 4
    },
    {
      "item": "chisel:concrete_lime1|4",
      "emc": 4
    },
    {
      "item": "chisel:concrete_lime1|5",
      "emc": 4
    },
    {
      "item": "chisel:concrete_lime1|6",
      "emc": 4
    },
    {
      "item": "chisel:concrete_lime1|7",
      "emc": 4
    },
    {
      "item": "chisel:concrete_lime1|8",
      "emc": 4
    },
    {
      "item": "chisel:concrete_lime1|9",
      "emc": 4
    },
    {
      "item": "chisel:concrete_lime1|10",
      "emc": 4
    },
    {
      "item": "chisel:concrete_lime1|11",
      "emc": 4
    },
    {
      "item": "chisel:concrete_lime1|12",
      "emc": 4
    },
    {
      "item": "chisel:concrete_lime1|13",
      "emc": 4
    },
    {
      "item": "chisel:concrete_lime1|14",
      "emc": 4
    },
    {
      "item": "chisel:concrete_lime1|15",
      "emc": 4
    },
    {
      "item": "chisel:concrete_lime2|0",
      "emc": 4
    },
    {
      "item": "chisel:concrete_yellow|0",
      "emc": 4
    },
    {
      "item": "chisel:concrete_yellow|1",
      "emc": 4
    },
    {
      "item": "chisel:concrete_yellow|2",
      "emc": 4
    },
    {
      "item": "chisel:concrete_yellow|3",
      "emc": 4
    },
    {
      "item": "chisel:concrete_yellow|4",
      "emc": 4
    },
    {
      "item": "chisel:concrete_yellow|5",
      "emc": 4
    },
    {
      "item": "chisel:concrete_yellow|6",
      "emc": 4
    },
    {
      "item": "chisel:concrete_yellow|7",
      "emc": 4
    },
    {
      "item": "chisel:concrete_yellow|8",
      "emc": 4
    },
    {
      "item": "chisel:concrete_yellow|9",
      "emc": 4
    },
    {
      "item": "chisel:concrete_yellow|10",
      "emc": 4
    },
    {
      "item": "chisel:concrete_yellow|11",
      "emc": 4
    },
    {
      "item": "chisel:concrete_yellow|12",
      "emc": 4
    },
    {
      "item": "chisel:concrete_yellow|13",
      "emc": 4
    },
    {
      "item": "chisel:concrete_yellow|14",
      "emc": 4
    },
    {
      "item": "chisel:concrete_yellow|15",
      "emc": 4
    },
    {
      "item": "chisel:concrete_yellow1|0",
      "emc": 4
    },
    {
      "item": "chisel:concrete_yellow1|1",
      "emc": 4
    },
    {
      "item": "chisel:concrete_yellow1|2",
      "emc": 4
    },
    {
      "item": "chisel:concrete_yellow1|3",
      "emc": 4
    },
    {
      "item": "chisel:concrete_yellow1|4",
      "emc": 4
    },
    {
      "item": "chisel:concrete_yellow1|5",
      "emc": 4
    },
    {
      "item": "chisel:concrete_yellow1|6",
      "emc": 4
    },
    {
      "item": "chisel:concrete_yellow1|7",
      "emc": 4
    },
    {
      "item": "chisel:concrete_yellow1|8",
      "emc": 4
    },
    {
      "item": "chisel:concrete_yellow1|9",
      "emc": 4
    },
    {
      "item": "chisel:concrete_yellow1|10",
      "emc": 4
    },
    {
      "item": "chisel:concrete_yellow1|11",
      "emc": 4
    },
    {
      "item": "chisel:concrete_yellow1|12",
      "emc": 4
    },
    {
      "item": "chisel:concrete_yellow1|13",
      "emc": 4
    },
    {
      "item": "chisel:concrete_yellow1|14",
      "emc": 4
    },
    {
      "item": "chisel:concrete_yellow1|15",
      "emc": 4
    },
    {
      "item": "chisel:concrete_yellow2|0",
      "emc": 4
    },
    {
      "item": "chisel:concrete_lightblue|0",
      "emc": 4
    },
    {
      "item": "chisel:concrete_lightblue|1",
      "emc": 4
    },
    {
      "item": "chisel:concrete_lightblue|2",
      "emc": 4
    },
    {
      "item": "chisel:concrete_lightblue|3",
      "emc": 4
    },
    {
      "item": "chisel:concrete_lightblue|4",
      "emc": 4
    },
    {
      "item": "chisel:concrete_lightblue|5",
      "emc": 4
    },
    {
      "item": "chisel:concrete_lightblue|6",
      "emc": 4
    },
    {
      "item": "chisel:concrete_lightblue|7",
      "emc": 4
    },
    {
      "item": "chisel:concrete_lightblue|8",
      "emc": 4
    },
    {
      "item": "chisel:concrete_lightblue|9",
      "emc": 4
    },
    {
      "item": "chisel:concrete_lightblue|10",
      "emc": 4
    },
    {
      "item": "chisel:concrete_lightblue|11",
      "emc": 4
    },
    {
      "item": "chisel:concrete_lightblue|12",
      "emc": 4
    },
    {
      "item": "chisel:concrete_lightblue|13",
      "emc": 4
    },
    {
      "item": "chisel:concrete_lightblue|14",
      "emc": 4
    },
    {
      "item": "chisel:concrete_lightblue|15",
      "emc": 4
    },
    {
      "item": "chisel:concrete_lightblue1|0",
      "emc": 4
    },
    {
      "item": "chisel:concrete_lightblue1|1",
      "emc": 4
    },
    {
      "item": "chisel:concrete_lightblue1|2",
      "emc": 4
    },
    {
      "item": "chisel:concrete_lightblue1|3",
      "emc": 4
    },
    {
      "item": "chisel:concrete_lightblue1|4",
      "emc": 4
    },
    {
      "item": "chisel:concrete_lightblue1|5",
      "emc": 4
    },
    {
      "item": "chisel:concrete_lightblue1|6",
      "emc": 4
    },
    {
      "item": "chisel:concrete_lightblue1|7",
      "emc": 4
    },
    {
      "item": "chisel:concrete_lightblue1|8",
      "emc": 4
    },
    {
      "item": "chisel:concrete_lightblue1|9",
      "emc": 4
    },
    {
      "item": "chisel:concrete_lightblue1|10",
      "emc": 4
    },
    {
      "item": "chisel:concrete_lightblue1|11",
      "emc": 4
    },
    {
      "item": "chisel:concrete_lightblue1|12",
      "emc": 4
    },
    {
      "item": "chisel:concrete_lightblue1|13",
      "emc": 4
    },
    {
      "item": "chisel:concrete_lightblue1|14",
      "emc": 4
    },
    {
      "item": "chisel:concrete_lightblue1|15",
      "emc": 4
    },
    {
      "item": "chisel:concrete_lightblue2|0",
      "emc": 4
    },
    {
      "item": "chisel:concrete_magenta|0",
      "emc": 4
    },
    {
      "item": "chisel:concrete_magenta|1",
      "emc": 4
    },
    {
      "item": "chisel:concrete_magenta|2",
      "emc": 4
    },
    {
      "item": "chisel:concrete_magenta|3",
      "emc": 4
    },
    {
      "item": "chisel:concrete_magenta|4",
      "emc": 4
    },
    {
      "item": "chisel:concrete_magenta|5",
      "emc": 4
    },
    {
      "item": "chisel:concrete_magenta|6",
      "emc": 4
    },
    {
      "item": "chisel:concrete_magenta|7",
      "emc": 4
    },
    {
      "item": "chisel:concrete_magenta|8",
      "emc": 4
    },
    {
      "item": "chisel:concrete_magenta|9",
      "emc": 4
    },
    {
      "item": "chisel:concrete_magenta|10",
      "emc": 4
    },
    {
      "item": "chisel:concrete_magenta|11",
      "emc": 4
    },
    {
      "item": "chisel:concrete_magenta|12",
      "emc": 4
    },
    {
      "item": "chisel:concrete_magenta|13",
      "emc": 4
    },
    {
      "item": "chisel:concrete_magenta|14",
      "emc": 4
    },
    {
      "item": "chisel:concrete_magenta|15",
      "emc": 4
    },
    {
      "item": "chisel:concrete_magenta1|0",
      "emc": 4
    },
    {
      "item": "chisel:concrete_magenta1|1",
      "emc": 4
    },
    {
      "item": "chisel:concrete_magenta1|2",
      "emc": 4
    },
    {
      "item": "chisel:concrete_magenta1|3",
      "emc": 4
    },
    {
      "item": "chisel:concrete_magenta1|4",
      "emc": 4
    },
    {
      "item": "chisel:concrete_magenta1|5",
      "emc": 4
    },
    {
      "item": "chisel:concrete_magenta1|6",
      "emc": 4
    },
    {
      "item": "chisel:concrete_magenta1|7",
      "emc": 4
    },
    {
      "item": "chisel:concrete_magenta1|8",
      "emc": 4
    },
    {
      "item": "chisel:concrete_magenta1|9",
      "emc": 4
    },
    {
      "item": "chisel:concrete_magenta1|10",
      "emc": 4
    },
    {
      "item": "chisel:concrete_magenta1|11",
      "emc": 4
    },
    {
      "item": "chisel:concrete_magenta1|12",
      "emc": 4
    },
    {
      "item": "chisel:concrete_magenta1|13",
      "emc": 4
    },
    {
      "item": "chisel:concrete_magenta1|14",
      "emc": 4
    },
    {
      "item": "chisel:concrete_magenta1|15",
      "emc": 4
    },
    {
      "item": "chisel:concrete_magenta2|0",
      "emc": 4
    },
    {
      "item": "chisel:concrete_orange|0",
      "emc": 4
    },
    {
      "item": "chisel:concrete_orange|1",
      "emc": 4
    },
    {
      "item": "chisel:concrete_orange|2",
      "emc": 4
    },
    {
      "item": "chisel:concrete_orange|3",
      "emc": 4
    },
    {
      "item": "chisel:concrete_orange|4",
      "emc": 4
    },
    {
      "item": "chisel:concrete_orange|5",
      "emc": 4
    },
    {
      "item": "chisel:concrete_orange|6",
      "emc": 4
    },
    {
      "item": "chisel:concrete_orange|7",
      "emc": 4
    },
    {
      "item": "chisel:concrete_orange|8",
      "emc": 4
    },
    {
      "item": "chisel:concrete_orange|9",
      "emc": 4
    },
    {
      "item": "chisel:concrete_orange|10",
      "emc": 4
    },
    {
      "item": "chisel:concrete_orange|11",
      "emc": 4
    },
    {
      "item": "chisel:concrete_orange|12",
      "emc": 4
    },
    {
      "item": "chisel:concrete_orange|13",
      "emc": 4
    },
    {
      "item": "chisel:concrete_orange|14",
      "emc": 4
    },
    {
      "item": "chisel:concrete_orange|15",
      "emc": 4
    },
    {
      "item": "chisel:concrete_orange1|0",
      "emc": 4
    },
    {
      "item": "chisel:concrete_orange1|1",
      "emc": 4
    },
    {
      "item": "chisel:concrete_orange1|2",
      "emc": 4
    },
    {
      "item": "chisel:concrete_orange1|3",
      "emc": 4
    },
    {
      "item": "chisel:concrete_orange1|4",
      "emc": 4
    },
    {
      "item": "chisel:concrete_orange1|5",
      "emc": 4
    },
    {
      "item": "chisel:concrete_orange1|6",
      "emc": 4
    },
    {
      "item": "chisel:concrete_orange1|7",
      "emc": 4
    },
    {
      "item": "chisel:concrete_orange1|8",
      "emc": 4
    },
    {
      "item": "chisel:concrete_orange1|9",
      "emc": 4
    },
    {
      "item": "chisel:concrete_orange1|10",
      "emc": 4
    },
    {
      "item": "chisel:concrete_orange1|12",
      "emc": 4
    },
    {
      "item": "chisel:concrete_orange1|13",
      "emc": 4
    },
    {
      "item": "chisel:concrete_orange1|14",
      "emc": 4
    },
    {
      "item": "chisel:concrete_orange1|15",
      "emc": 4
    },
    {
      "item": "chisel:concrete_orange2|0",
      "emc": 4
    },
    {
      "item": "chisel:concrete_white|0",
      "emc": 4
    },
    {
      "item": "chisel:concrete_white|1",
      "emc": 4
    },
    {
      "item": "chisel:concrete_white|2",
      "emc": 4
    },
    {
      "item": "chisel:concrete_white|3",
      "emc": 4
    },
    {
      "item": "chisel:concrete_white|4",
      "emc": 4
    },
    {
      "item": "chisel:concrete_white|5",
      "emc": 4
    },
    {
      "item": "chisel:concrete_white|6",
      "emc": 4
    },
    {
      "item": "chisel:concrete_white|7",
      "emc": 4
    },
    {
      "item": "chisel:concrete_white|8",
      "emc": 4
    },
    {
      "item": "chisel:concrete_white|9",
      "emc": 4
    },
    {
      "item": "chisel:concrete_white|10",
      "emc": 4
    },
    {
      "item": "chisel:concrete_white|11",
      "emc": 4
    },
    {
      "item": "chisel:concrete_white|12",
      "emc": 4
    },
    {
      "item": "chisel:concrete_white|13",
      "emc": 4
    },
    {
      "item": "chisel:concrete_white|14",
      "emc": 4
    },
    {
      "item": "chisel:concrete_white|15",
      "emc": 4
    },
    {
      "item": "chisel:concrete_white1|0",
      "emc": 4
    },
    {
      "item": "chisel:concrete_white1|1",
      "emc": 4
    },
    {
      "item": "chisel:concrete_white1|2",
      "emc": 4
    },
    {
      "item": "chisel:concrete_white1|3",
      "emc": 4
    },
    {
      "item": "chisel:concrete_white1|4",
      "emc": 4
    },
    {
      "item": "chisel:concrete_white1|5",
      "emc": 4
    },
    {
      "item": "chisel:concrete_white1|6",
      "emc": 4
    },
    {
      "item": "chisel:concrete_white1|7",
      "emc": 4
    },
    {
      "item": "chisel:concrete_white1|8",
      "emc": 4
    },
    {
      "item": "chisel:concrete_white1|9",
      "emc": 4
    },
    {
      "item": "chisel:concrete_white1|10",
      "emc": 4
    },
    {
      "item": "chisel:concrete_white1|11",
      "emc": 4
    },
    {
      "item": "chisel:concrete_white1|12",
      "emc": 4
    },
    {
      "item": "chisel:concrete_white1|13",
      "emc": 4
    },
    {
      "item": "chisel:concrete_white1|14",
      "emc": 4
    },
    {
      "item": "chisel:concrete_white1|15",
      "emc": 4
    },
    {
      "item": "chisel:concrete_white2|0",
      "emc": 4
    },
    {
      "item": "chisel:blockcopper|0",
      "emc": 1152
    },
    {
      "item": "chisel:blockcopper|1",
      "emc": 1152
    },
    {
      "item": "chisel:blockcopper|2",
      "emc": 1152
    },
    {
      "item": "chisel:blockcopper|3",
      "emc": 1152
    },
    {
      "item": "chisel:blockcopper|4",
      "emc": 1152
    },
    {
      "item": "chisel:blockcopper|5",
      "emc": 1152
    },
    {
      "item": "chisel:blockcopper|6",
      "emc": 1152
    },
    {
      "item": "chisel:diamond|6",
      "emc": 73728
    },
    {
      "item": "chisel:diamond|0",
      "emc": 73728
    },
    {
      "item": "chisel:diamond|1",
      "emc": 73728
    },
    {
      "item": "chisel:diamond|2",
      "emc": 73728
    },
    {
      "item": "chisel:diamond|3",
      "emc": 73728
    },
    {
      "item": "chisel:diamond|4",
      "emc": 73728
    },
    {
      "item": "chisel:diamond|5",
      "emc": 73728
    },
    {
      "item": "chisel:diamond|7",
      "emc": 73728
    },
    {
      "item": "chisel:diamond|8",
      "emc": 73728
    },
    {
      "item": "chisel:diamond|10",
      "emc": 73728
    },
    {
      "item": "chisel:diamond|9",
      "emc": 73728
    },
    {
      "item": "chisel:diamond|11",
      "emc": 73728
    },
    {
      "item": "chisel:diorite|0",
      "emc": 16
    },
    {
      "item": "chisel:diorite|1",
      "emc": 16
    },
    {
      "item": "chisel:diorite|2",
      "emc": 16
    },
    {
      "item": "chisel:diorite|3",
      "emc": 16
    },
    {
      "item": "chisel:diorite|4",
      "emc": 16
    },
    {
      "item": "chisel:diorite|5",
      "emc": 16
    },
    {
      "item": "chisel:diorite|6",
      "emc": 16
    },
    {
      "item": "chisel:diorite|7",
      "emc": 16
    },
    {
      "item": "chisel:diorite|8",
      "emc": 16
    },
    {
      "item": "chisel:diorite|9",
      "emc": 16
    },
    {
      "item": "chisel:diorite|10",
      "emc": 16
    },
    {
      "item": "chisel:diorite|11",
      "emc": 16
    },
    {
      "item": "chisel:diorite|12",
      "emc": 16
    },
    {
      "item": "chisel:diorite|13",
      "emc": 16
    },
    {
      "item": "chisel:diorite|14",
      "emc": 16
    },
    {
      "item": "chisel:diorite|15",
      "emc": 16
    },
    {
      "item": "chisel:diorite1|0",
      "emc": 16
    },
    {
      "item": "chisel:diorite1|1",
      "emc": 16
    },
    {
      "item": "chisel:diorite1|2",
      "emc": 16
    },
    {
      "item": "chisel:diorite1|3",
      "emc": 16
    },
    {
      "item": "chisel:diorite1|4",
      "emc": 16
    },
    {
      "item": "chisel:diorite1|5",
      "emc": 16
    },
    {
      "item": "chisel:diorite1|6",
      "emc": 16
    },
    {
      "item": "chisel:diorite1|7",
      "emc": 16
    },
    {
      "item": "chisel:diorite1|8",
      "emc": 16
    },
    {
      "item": "chisel:diorite1|9",
      "emc": 16
    },
    {
      "item": "chisel:diorite1|10",
      "emc": 16
    },
    {
      "item": "chisel:diorite1|11",
      "emc": 16
    },
    {
      "item": "chisel:diorite1|12",
      "emc": 16
    },
    {
      "item": "chisel:diorite1|13",
      "emc": 16
    },
    {
      "item": "chisel:diorite1|14",
      "emc": 16
    },
    {
      "item": "chisel:diorite2|0",
      "emc": 16
    },
    {
      "item": "chisel:diorite1|15",
      "emc": 16
    },
    {
      "item": "chisel:dirt|0",
      "emc": 1
    },
    {
      "item": "chisel:dirt|1",
      "emc": 1
    },
    {
      "item": "chisel:dirt|2",
      "emc": 1
    },
    {
      "item": "chisel:dirt|3",
      "emc": 1
    },
    {
      "item": "chisel:dirt|4",
      "emc": 1
    },
    {
      "item": "chisel:dirt|5",
      "emc": 1
    },
    {
      "item": "chisel:dirt|6",
      "emc": 1
    },
    {
      "item": "chisel:dirt|7",
      "emc": 1
    },
    {
      "item": "chisel:dirt|8",
      "emc": 1
    },
    {
      "item": "chisel:dirt|9",
      "emc": 1
    },
    {
      "item": "chisel:dirt|10",
      "emc": 1
    },
    {
      "item": "chisel:dirt|11",
      "emc": 1
    },
    {
      "item": "chisel:dirt|12",
      "emc": 1
    },
    {
      "item": "chisel:dirt|13",
      "emc": 1
    },
    {
      "item": "chisel:dirt|14",
      "emc": 1
    },
    {
      "item": "chisel:dirt|15",
      "emc": 1
    },
    {
      "item": "chisel:blockelectrum|0",
      "emc": 11520
    },
    {
      "item": "chisel:blockelectrum|1",
      "emc": 11520
    },
    {
      "item": "chisel:blockelectrum|2",
      "emc": 11520
    },
    {
      "item": "chisel:blockelectrum|3",
      "emc": 11520
    },
    {
      "item": "chisel:blockelectrum|4",
      "emc": 11520
    },
    {
      "item": "chisel:blockelectrum|5",
      "emc": 11520
    },
    {
      "item": "chisel:blockelectrum|6",
      "emc": 11520
    },
    {
      "item": "chisel:emerald|6",
      "emc": 147456
    },
    {
      "item": "chisel:emerald|0",
      "emc": 147456
    },
    {
      "item": "chisel:emerald|1",
      "emc": 147456
    },
    {
      "item": "chisel:emerald|2",
      "emc": 147456
    },
    {
      "item": "chisel:emerald|3",
      "emc": 147456
    },
    {
      "item": "chisel:emerald|4",
      "emc": 147456
    },
    {
      "item": "chisel:emerald|5",
      "emc": 147456
    },
    {
      "item": "chisel:emerald|7",
      "emc": 147456
    },
    {
      "item": "chisel:emerald|8",
      "emc": 147456
    },
    {
      "item": "chisel:emerald|9",
      "emc": 147456
    },
    {
      "item": "chisel:emerald|10",
      "emc": 147456
    },
    {
      "item": "chisel:emerald|11",
      "emc": 147456
    },
    {
      "item": "chisel:emerald|12",
      "emc": 147456
    },
    {
      "item": "chisel:emerald|13",
      "emc": 147456
    },
    {
      "item": "chisel:purpur|0",
      "emc": 192
    },
    {
      "item": "chisel:purpur|1",
      "emc": 192
    },
    {
      "item": "chisel:purpur|2",
      "emc": 192
    },
    {
      "item": "chisel:purpur|3",
      "emc": 192
    },
    {
      "item": "chisel:purpur|4",
      "emc": 192
    },
    {
      "item": "chisel:purpur|5",
      "emc": 192
    },
    {
      "item": "chisel:purpur|6",
      "emc": 192
    },
    {
      "item": "chisel:purpur|7",
      "emc": 192
    },
    {
      "item": "chisel:purpur|8",
      "emc": 192
    },
    {
      "item": "chisel:purpur|9",
      "emc": 192
    },
    {
      "item": "chisel:purpur|10",
      "emc": 192
    },
    {
      "item": "chisel:purpur|11",
      "emc": 192
    },
    {
      "item": "chisel:purpur|12",
      "emc": 192
    },
    {
      "item": "chisel:purpur|13",
      "emc": 192
    },
    {
      "item": "chisel:purpur|14",
      "emc": 192
    },
    {
      "item": "chisel:purpur|15",
      "emc": 192
    },
    {
      "item": "chisel:purpur1|0",
      "emc": 192
    },
    {
      "item": "chisel:purpur1|1",
      "emc": 192
    },
    {
      "item": "chisel:purpur1|2",
      "emc": 192
    },
    {
      "item": "chisel:purpur1|3",
      "emc": 192
    },
    {
      "item": "chisel:purpur1|4",
      "emc": 192
    },
    {
      "item": "chisel:purpur1|5",
      "emc": 192
    },
    {
      "item": "chisel:purpur1|6",
      "emc": 192
    },
    {
      "item": "chisel:purpur1|7",
      "emc": 192
    },
    {
      "item": "chisel:purpur1|8",
      "emc": 192
    },
    {
      "item": "chisel:purpur1|9",
      "emc": 192
    },
    {
      "item": "chisel:purpur2|0",
      "emc": 192
    },
    {
      "item": "chisel:purpur2|1",
      "emc": 192
    },
    {
      "item": "chisel:purpur2|2",
      "emc": 192
    },
    {
      "item": "chisel:purpur2|4",
      "emc": 192
    },
    {
      "item": "chisel:purpur2|3",
      "emc": 192
    },
    {
      "item": "chisel:endstone|0",
      "emc": 1
    },
    {
      "item": "chisel:endstone|1",
      "emc": 1
    },
    {
      "item": "chisel:endstone|2",
      "emc": 1
    },
    {
      "item": "chisel:endstone|3",
      "emc": 1
    },
    {
      "item": "chisel:endstone|4",
      "emc": 1
    },
    {
      "item": "chisel:endstone|5",
      "emc": 1
    },
    {
      "item": "chisel:endstone|6",
      "emc": 1
    },
    {
      "item": "chisel:endstone|7",
      "emc": 1
    },
    {
      "item": "chisel:endstone|8",
      "emc": 1
    },
    {
      "item": "chisel:endstone|9",
      "emc": 1
    },
    {
      "item": "chisel:endstone|10",
      "emc": 1
    },
    {
      "item": "chisel:endstone|11",
      "emc": 1
    },
    {
      "item": "chisel:endstone|12",
      "emc": 1
    },
    {
      "item": "chisel:endstone|13",
      "emc": 1
    },
    {
      "item": "chisel:endstone|14",
      "emc": 1
    },
    {
      "item": "chisel:endstone|15",
      "emc": 1
    },
    {
      "item": "chisel:endstone1|0",
      "emc": 1
    },
    {
      "item": "chisel:endstone1|1",
      "emc": 1
    },
    {
      "item": "chisel:endstone1|2",
      "emc": 1
    },
    {
      "item": "chisel:endstone1|3",
      "emc": 1
    },
    {
      "item": "chisel:endstone1|4",
      "emc": 1
    },
    {
      "item": "chisel:endstone1|5",
      "emc": 1
    },
    {
      "item": "chisel:endstone1|6",
      "emc": 1
    },
    {
      "item": "chisel:endstone1|7",
      "emc": 1
    },
    {
      "item": "chisel:endstone1|8",
      "emc": 1
    },
    {
      "item": "chisel:endstone1|9",
      "emc": 1
    },
    {
      "item": "chisel:endstone2|0",
      "emc": 1
    },
    {
      "item": "chisel:endstone2|1",
      "emc": 1
    },
    {
      "item": "chisel:endstone2|2",
      "emc": 1
    },
    {
      "item": "chisel:endstone2|3",
      "emc": 1
    },
    {
      "item": "chisel:endstone2|4",
      "emc": 1
    },
    {
      "item": "chisel:endstone2|5",
      "emc": 1
    },
    {
      "item": "chisel:endstone2|6",
      "emc": 1
    },
    {
      "item": "chisel:factory|1",
      "emc": 32
    },
    {
      "item": "chisel:factory|2",
      "emc": 32
    },
    {
      "item": "chisel:factory|3",
      "emc": 32
    },
    {
      "item": "chisel:factory|4",
      "emc": 32
    },
    {
      "item": "chisel:factory|5",
      "emc": 32
    },
    {
      "item": "chisel:factory|6",
      "emc": 32
    },
    {
      "item": "chisel:factory|7",
      "emc": 32
    },
    {
      "item": "chisel:factory|8",
      "emc": 32
    },
    {
      "item": "chisel:factory|9",
      "emc": 32
    },
    {
      "item": "chisel:factory|10",
      "emc": 32
    },
    {
      "item": "chisel:factory|11",
      "emc": 32
    },
    {
      "item": "chisel:factory|12",
      "emc": 32
    },
    {
      "item": "chisel:factory|13",
      "emc": 32
    },
    {
      "item": "chisel:factory|14",
      "emc": 32
    },
    {
      "item": "chisel:factory|15",
      "emc": 32
    },
    {
      "item": "chisel:factory1|0",
      "emc": 32
    },
    {
      "item": "chisel:factory1|1",
      "emc": 32
    },
    {
      "item": "chisel:factory1|2",
      "emc": 32
    },
    {
      "item": "chisel:factory1|3",
      "emc": 32
    },
    {
      "item": "chisel:factory1|4",
      "emc": 32
    },
    {
      "item": "chisel:futura|1",
      "emc": 9
    },
    {
      "item": "chisel:futura|2",
      "emc": 9
    },
    {
      "item": "chisel:futura|3",
      "emc": 9
    },
    {
      "item": "chisel:futura|4",
      "emc": 9
    },
    {
      "item": "chisel:futura|5",
      "emc": 9
    },
    {
      "item": "chisel:glowstone|4",
      "emc": 1536
    },
    {
      "item": "chisel:glowstone|0",
      "emc": 1536
    },
    {
      "item": "chisel:glowstone|1",
      "emc": 1536
    },
    {
      "item": "chisel:glowstone|2",
      "emc": 1536
    },
    {
      "item": "chisel:glowstone|3",
      "emc": 1536
    },
    {
      "item": "chisel:glowstone|5",
      "emc": 1536
    },
    {
      "item": "chisel:glowstone|6",
      "emc": 1536
    },
    {
      "item": "chisel:glowstone|7",
      "emc": 1536
    },
    {
      "item": "chisel:glowstone|8",
      "emc": 1536
    },
    {
      "item": "chisel:glowstone|9",
      "emc": 1536
    },
    {
      "item": "chisel:glowstone|10",
      "emc": 1536
    },
    {
      "item": "chisel:glowstone|11",
      "emc": 1536
    },
    {
      "item": "chisel:glowstone|12",
      "emc": 1536
    },
    {
      "item": "chisel:glowstone|13",
      "emc": 1536
    },
    {
      "item": "chisel:glowstone|14",
      "emc": 1536
    },
    {
      "item": "chisel:glowstone|15",
      "emc": 1536
    },
    {
      "item": "chisel:glowstone1|0",
      "emc": 1536
    },
    {
      "item": "chisel:glowstone1|1",
      "emc": 1536
    },
    {
      "item": "chisel:glowstone1|2",
      "emc": 1536
    },
    {
      "item": "chisel:glowstone1|3",
      "emc": 1536
    },
    {
      "item": "chisel:glowstone1|4",
      "emc": 1536
    },
    {
      "item": "chisel:glowstone1|5",
      "emc": 1536
    },
    {
      "item": "chisel:glowstone1|6",
      "emc": 1536
    },
    {
      "item": "chisel:glowstone1|7",
      "emc": 1536
    },
    {
      "item": "chisel:glowstone1|8",
      "emc": 1536
    },
    {
      "item": "chisel:glowstone1|9",
      "emc": 1536
    },
    {
      "item": "chisel:glowstone1|10",
      "emc": 1536
    },
    {
      "item": "chisel:glowstone1|11",
      "emc": 1536
    },
    {
      "item": "chisel:glowstone1|12",
      "emc": 1536
    },
    {
      "item": "chisel:glowstone1|13",
      "emc": 1536
    },
    {
      "item": "chisel:glowstone1|14",
      "emc": 1536
    },
    {
      "item": "chisel:glowstone1|15",
      "emc": 1536
    },
    {
      "item": "chisel:glowstone2|0",
      "emc": 1536
    },
    {
      "item": "chisel:blockgold|0",
      "emc": 18432
    },
    {
      "item": "chisel:blockgold|1",
      "emc": 18432
    },
    {
      "item": "chisel:blockgold|2",
      "emc": 18432
    },
    {
      "item": "chisel:blockgold|3",
      "emc": 18432
    },
    {
      "item": "chisel:blockgold|4",
      "emc": 18432
    },
    {
      "item": "chisel:blockgold|5",
      "emc": 18432
    },
    {
      "item": "chisel:blockgold|6",
      "emc": 18432
    },
    {
      "item": "chisel:gold|0",
      "emc": 18432
    },
    {
      "item": "chisel:gold|1",
      "emc": 18432
    },
    {
      "item": "chisel:gold|2",
      "emc": 18432
    },
    {
      "item": "chisel:gold|3",
      "emc": 18432
    },
    {
      "item": "chisel:gold|4",
      "emc": 18432
    },
    {
      "item": "chisel:gold|5",
      "emc": 18432
    },
    {
      "item": "chisel:gold|6",
      "emc": 18432
    },
    {
      "item": "chisel:gold|7",
      "emc": 18432
    },
    {
      "item": "chisel:gold|8",
      "emc": 18432
    },
    {
      "item": "chisel:gold|9",
      "emc": 18432
    },
    {
      "item": "chisel:gold|10",
      "emc": 18432
    },
    {
      "item": "chisel:gold|11",
      "emc": 18432
    },
    {
      "item": "chisel:gold|12",
      "emc": 18432
    },
    {
      "item": "chisel:gold|13",
      "emc": 18432
    },
    {
      "item": "chisel:granite|0",
      "emc": 16
    },
    {
      "item": "chisel:granite|1",
      "emc": 16
    },
    {
      "item": "chisel:granite|2",
      "emc": 16
    },
    {
      "item": "chisel:granite|3",
      "emc": 16
    },
    {
      "item": "chisel:granite|4",
      "emc": 16
    },
    {
      "item": "chisel:granite|5",
      "emc": 16
    },
    {
      "item": "chisel:granite|6",
      "emc": 16
    },
    {
      "item": "chisel:granite|7",
      "emc": 16
    },
    {
      "item": "chisel:granite|8",
      "emc": 16
    },
    {
      "item": "chisel:granite|9",
      "emc": 16
    },
    {
      "item": "chisel:granite|10",
      "emc": 16
    },
    {
      "item": "chisel:granite|11",
      "emc": 16
    },
    {
      "item": "chisel:granite|12",
      "emc": 16
    },
    {
      "item": "chisel:granite|13",
      "emc": 16
    },
    {
      "item": "chisel:granite|14",
      "emc": 16
    },
    {
      "item": "chisel:granite|15",
      "emc": 16
    },
    {
      "item": "chisel:granite1|0",
      "emc": 16
    },
    {
      "item": "chisel:granite1|1",
      "emc": 16
    },
    {
      "item": "chisel:granite1|2",
      "emc": 16
    },
    {
      "item": "chisel:granite1|3",
      "emc": 16
    },
    {
      "item": "chisel:granite1|4",
      "emc": 16
    },
    {
      "item": "chisel:granite1|5",
      "emc": 16
    },
    {
      "item": "chisel:granite1|6",
      "emc": 16
    },
    {
      "item": "chisel:granite1|7",
      "emc": 16
    },
    {
      "item": "chisel:granite1|8",
      "emc": 16
    },
    {
      "item": "chisel:granite1|9",
      "emc": 16
    },
    {
      "item": "chisel:granite1|10",
      "emc": 16
    },
    {
      "item": "chisel:granite1|11",
      "emc": 16
    },
    {
      "item": "chisel:granite1|12",
      "emc": 16
    },
    {
      "item": "chisel:granite1|13",
      "emc": 16
    },
    {
      "item": "chisel:granite1|14",
      "emc": 16
    },
    {
      "item": "chisel:granite1|15",
      "emc": 16
    },
    {
      "item": "chisel:granite2|0",
      "emc": 16
    },
    {
      "item": "chisel:hardenedclay|0",
      "emc": 64
    },
    {
      "item": "chisel:hardenedclay|1",
      "emc": 64
    },
    {
      "item": "chisel:hardenedclay|2",
      "emc": 64
    },
    {
      "item": "chisel:hardenedclay|3",
      "emc": 64
    },
    {
      "item": "chisel:hardenedclay|4",
      "emc": 64
    },
    {
      "item": "chisel:hardenedclay|5",
      "emc": 64
    },
    {
      "item": "chisel:hardenedclay|6",
      "emc": 64
    },
    {
      "item": "chisel:hardenedclay|7",
      "emc": 64
    },
    {
      "item": "chisel:hardenedclay|8",
      "emc": 64
    },
    {
      "item": "chisel:hardenedclay|9",
      "emc": 64
    },
    {
      "item": "chisel:hardenedclay|10",
      "emc": 64
    },
    {
      "item": "chisel:hardenedclay|11",
      "emc": 64
    },
    {
      "item": "chisel:hardenedclay|12",
      "emc": 64
    },
    {
      "item": "chisel:hardenedclay|13",
      "emc": 64
    },
    {
      "item": "chisel:hardenedclay|14",
      "emc": 64
    },
    {
      "item": "chisel:hardenedclay|15",
      "emc": 64
    },
    {
      "item": "chisel:hardenedclay1|0",
      "emc": 64
    },
    {
      "item": "chisel:hardenedclay1|1",
      "emc": 64
    },
    {
      "item": "chisel:hardenedclay1|2",
      "emc": 64
    },
    {
      "item": "chisel:hardenedclay1|3",
      "emc": 64
    },
    {
      "item": "chisel:hardenedclay1|4",
      "emc": 64
    },
    {
      "item": "chisel:hardenedclay1|5",
      "emc": 64
    },
    {
      "item": "chisel:hardenedclay1|6",
      "emc": 64
    },
    {
      "item": "chisel:hardenedclay1|7",
      "emc": 64
    },
    {
      "item": "chisel:hardenedclay1|8",
      "emc": 64
    },
    {
      "item": "chisel:hardenedclay1|9",
      "emc": 64
    },
    {
      "item": "chisel:hardenedclay2|0",
      "emc": 64
    },
    {
      "item": "chisel:hardenedclay2|1",
      "emc": 64
    },
    {
      "item": "chisel:hardenedclay2|2",
      "emc": 64
    },
    {
      "item": "chisel:hardenedclay2|3",
      "emc": 64
    },
    {
      "item": "chisel:hardenedclay2|4",
      "emc": 64
    },
    {
      "item": "chisel:hardenedclay2|5",
      "emc": 64
    },
    {
      "item": "chisel:hardenedclay2|6",
      "emc": 64
    },
    {
      "item": "chisel:ice|0",
      "emc": 1
    },
    {
      "item": "chisel:ice|1",
      "emc": 1
    },
    {
      "item": "chisel:ice|2",
      "emc": 1
    },
    {
      "item": "chisel:ice|3",
      "emc": 1
    },
    {
      "item": "chisel:ice|4",
      "emc": 1
    },
    {
      "item": "chisel:ice|5",
      "emc": 1
    },
    {
      "item": "chisel:ice|6",
      "emc": 1
    },
    {
      "item": "chisel:ice|7",
      "emc": 1
    },
    {
      "item": "chisel:ice|8",
      "emc": 1
    },
    {
      "item": "chisel:ice|9",
      "emc": 1
    },
    {
      "item": "chisel:ice|10",
      "emc": 1
    },
    {
      "item": "chisel:ice|11",
      "emc": 1
    },
    {
      "item": "chisel:ice|12",
      "emc": 1
    },
    {
      "item": "chisel:ice|13",
      "emc": 1
    },
    {
      "item": "chisel:ice|14",
      "emc": 1
    },
    {
      "item": "chisel:ice|15",
      "emc": 1
    },
    {
      "item": "chisel:ice1|0",
      "emc": 1
    },
    {
      "item": "chisel:ice1|1",
      "emc": 1
    },
    {
      "item": "chisel:ice1|2",
      "emc": 1
    },
    {
      "item": "chisel:ice1|3",
      "emc": 1
    },
    {
      "item": "chisel:ice1|4",
      "emc": 1
    },
    {
      "item": "chisel:ice1|5",
      "emc": 1
    },
    {
      "item": "chisel:ice1|6",
      "emc": 1
    },
    {
      "item": "chisel:ice1|7",
      "emc": 1
    },
    {
      "item": "chisel:ice1|8",
      "emc": 1
    },
    {
      "item": "chisel:ice1|9",
      "emc": 1
    },
    {
      "item": "chisel:ice1|10",
      "emc": 1
    },
    {
      "item": "chisel:ice1|11",
      "emc": 1
    },
    {
      "item": "chisel:ice1|12",
      "emc": 1
    },
    {
      "item": "chisel:ice1|14",
      "emc": 1
    },
    {
      "item": "chisel:ice1|13",
      "emc": 1
    },
    {
      "item": "chisel:ice1|15",
      "emc": 1
    },
    {
      "item": "chisel:ice2|0",
      "emc": 1
    },
    {
      "item": "chisel:icepillar|0",
      "emc": 1
    },
    {
      "item": "chisel:icepillar|1",
      "emc": 1
    },
    {
      "item": "chisel:icepillar|2",
      "emc": 1
    },
    {
      "item": "chisel:icepillar|3",
      "emc": 1
    },
    {
      "item": "chisel:icepillar|4",
      "emc": 1
    },
    {
      "item": "chisel:icepillar|5",
      "emc": 1
    },
    {
      "item": "chisel:icepillar|6",
      "emc": 1
    },
    {
      "item": "chisel:blockinvar|0",
      "emc": 4608
    },
    {
      "item": "chisel:blockinvar|1",
      "emc": 4608
    },
    {
      "item": "chisel:blockinvar|2",
      "emc": 4608
    },
    {
      "item": "chisel:blockinvar|3",
      "emc": 4608
    },
    {
      "item": "chisel:blockinvar|4",
      "emc": 4608
    },
    {
      "item": "chisel:blockinvar|5",
      "emc": 4608
    },
    {
      "item": "chisel:blockinvar|6",
      "emc": 4608
    },
    {
      "item": "chisel:blockiron|0",
      "emc": 2304
    },
    {
      "item": "chisel:blockiron|1",
      "emc": 2304
    },
    {
      "item": "chisel:iron|1",
      "emc": 2304
    },
    {
      "item": "chisel:blockiron|2",
      "emc": 2304
    },
    {
      "item": "chisel:blockiron|3",
      "emc": 2304
    },
    {
      "item": "chisel:blockiron|4",
      "emc": 2304
    },
    {
      "item": "chisel:blockiron|5",
      "emc": 2304
    },
    {
      "item": "chisel:blockiron|6",
      "emc": 2304
    },
    {
      "item": "chisel:iron|0",
      "emc": 2304
    },
    {
      "item": "chisel:iron|2",
      "emc": 2304
    },
    {
      "item": "chisel:iron|3",
      "emc": 2304
    },
    {
      "item": "chisel:iron|4",
      "emc": 2304
    },
    {
      "item": "chisel:iron|5",
      "emc": 2304
    },
    {
      "item": "chisel:iron|6",
      "emc": 2304
    },
    {
      "item": "chisel:iron|7",
      "emc": 2304
    },
    {
      "item": "chisel:iron|8",
      "emc": 2304
    },
    {
      "item": "chisel:iron|9",
      "emc": 2304
    },
    {
      "item": "chisel:iron|10",
      "emc": 2304
    },
    {
      "item": "chisel:iron|11",
      "emc": 2304
    },
    {
      "item": "chisel:iron|12",
      "emc": 2304
    },
    {
      "item": "chisel:iron|13",
      "emc": 2304
    },
    {
      "item": "chisel:iron|14",
      "emc": 2304
    },
    {
      "item": "chisel:ironpane|0",
      "emc": 96
    },
    {
      "item": "chisel:ironpane|1",
      "emc": 96
    },
    {
      "item": "chisel:ironpane|2",
      "emc": 96
    },
    {
      "item": "chisel:ironpane|3",
      "emc": 96
    },
    {
      "item": "chisel:ironpane|4",
      "emc": 96
    },
    {
      "item": "chisel:ironpane|5",
      "emc": 96
    },
    {
      "item": "chisel:ironpane|6",
      "emc": 96
    },
    {
      "item": "chisel:ironpane|7",
      "emc": 96
    },
    {
      "item": "chisel:ironpane|8",
      "emc": 96
    },
    {
      "item": "chisel:ironpane|9",
      "emc": 96
    },
    {
      "item": "chisel:ironpane|10",
      "emc": 96
    },
    {
      "item": "chisel:ironpane|11",
      "emc": 96
    },
    {
      "item": "chisel:ironpane|12",
      "emc": 96
    },
    {
      "item": "chisel:laboratory|1",
      "emc": 33
    },
    {
      "item": "chisel:laboratory|2",
      "emc": 33
    },
    {
      "item": "chisel:laboratory|3",
      "emc": 33
    },
    {
      "item": "chisel:laboratory|4",
      "emc": 33
    },
    {
      "item": "chisel:laboratory|5",
      "emc": 33
    },
    {
      "item": "chisel:laboratory|6",
      "emc": 33
    },
    {
      "item": "chisel:laboratory|7",
      "emc": 33
    },
    {
      "item": "chisel:laboratory|8",
      "emc": 33
    },
    {
      "item": "chisel:laboratory|9",
      "emc": 33
    },
    {
      "item": "chisel:laboratory|10",
      "emc": 33
    },
    {
      "item": "chisel:laboratory|11",
      "emc": 33
    },
    {
      "item": "chisel:laboratory|12",
      "emc": 33
    },
    {
      "item": "chisel:laboratory|13",
      "emc": 33
    },
    {
      "item": "chisel:laboratory|14",
      "emc": 33
    },
    {
      "item": "chisel:laboratory|15",
      "emc": 33
    },
    {
      "item": "chisel:lapis|0",
      "emc": 144
    },
    {
      "item": "chisel:lapis|1",
      "emc": 144
    },
    {
      "item": "chisel:lapis|2",
      "emc": 144
    },
    {
      "item": "chisel:lapis|3",
      "emc": 144
    },
    {
      "item": "chisel:lapis|4",
      "emc": 144
    },
    {
      "item": "chisel:lapis|5",
      "emc": 144
    },
    {
      "item": "chisel:lapis|6",
      "emc": 144
    },
    {
      "item": "chisel:lapis|7",
      "emc": 144
    },
    {
      "item": "chisel:lapis|8",
      "emc": 144
    },
    {
      "item": "chisel:lavastone|1",
      "emc": 9
    },
    {
      "item": "chisel:lavastone|2",
      "emc": 9
    },
    {
      "item": "chisel:lavastone|3",
      "emc": 9
    },
    {
      "item": "chisel:lavastone|4",
      "emc": 9
    },
    {
      "item": "chisel:lavastone|5",
      "emc": 9
    },
    {
      "item": "chisel:lavastone|6",
      "emc": 9
    },
    {
      "item": "chisel:lavastone|7",
      "emc": 9
    },
    {
      "item": "chisel:lavastone|8",
      "emc": 9
    },
    {
      "item": "chisel:lavastone|9",
      "emc": 9
    },
    {
      "item": "chisel:lavastone|10",
      "emc": 9
    },
    {
      "item": "chisel:lavastone|11",
      "emc": 9
    },
    {
      "item": "chisel:lavastone|12",
      "emc": 9
    },
    {
      "item": "chisel:lavastone|13",
      "emc": 9
    },
    {
      "item": "chisel:lavastone|14",
      "emc": 9
    },
    {
      "item": "chisel:lavastone|15",
      "emc": 9
    },
    {
      "item": "chisel:lavastone1|0",
      "emc": 9
    },
    {
      "item": "chisel:lavastone1|1",
      "emc": 9
    },
    {
      "item": "chisel:lavastone1|2",
      "emc": 9
    },
    {
      "item": "chisel:lavastone1|3",
      "emc": 9
    },
    {
      "item": "chisel:lavastone1|4",
      "emc": 9
    },
    {
      "item": "chisel:lavastone1|5",
      "emc": 9
    },
    {
      "item": "chisel:lavastone1|6",
      "emc": 9
    },
    {
      "item": "chisel:lavastone1|7",
      "emc": 9
    },
    {
      "item": "chisel:lavastone1|8",
      "emc": 9
    },
    {
      "item": "chisel:lavastone1|9",
      "emc": 9
    },
    {
      "item": "chisel:lavastone1|10",
      "emc": 9
    },
    {
      "item": "chisel:lavastone1|11",
      "emc": 9
    },
    {
      "item": "chisel:lavastone1|12",
      "emc": 9
    },
    {
      "item": "chisel:lavastone1|14",
      "emc": 9
    },
    {
      "item": "chisel:lavastone1|13",
      "emc": 9
    },
    {
      "item": "chisel:lavastone1|15",
      "emc": 9
    },
    {
      "item": "chisel:lavastone2|0",
      "emc": 9
    },
    {
      "item": "chisel:blocklead|0",
      "emc": 4608
    },
    {
      "item": "chisel:blocklead|1",
      "emc": 4608
    },
    {
      "item": "chisel:blocklead|2",
      "emc": 4608
    },
    {
      "item": "chisel:blocklead|3",
      "emc": 4608
    },
    {
      "item": "chisel:blocklead|4",
      "emc": 4608
    },
    {
      "item": "chisel:blocklead|5",
      "emc": 4608
    },
    {
      "item": "chisel:blocklead|6",
      "emc": 4608
    },
    {
      "item": "chisel:limestone|0",
      "emc": 4
    },
    {
      "item": "chisel:limestone|1",
      "emc": 4
    },
    {
      "item": "chisel:limestone|2",
      "emc": 4
    },
    {
      "item": "chisel:limestone|3",
      "emc": 4
    },
    {
      "item": "chisel:limestone|4",
      "emc": 4
    },
    {
      "item": "chisel:limestone|5",
      "emc": 4
    },
    {
      "item": "chisel:limestone|6",
      "emc": 4
    },
    {
      "item": "chisel:limestone|7",
      "emc": 4
    },
    {
      "item": "chisel:limestone|8",
      "emc": 4
    },
    {
      "item": "chisel:limestone|10",
      "emc": 4
    },
    {
      "item": "chisel:limestone|11",
      "emc": 4
    },
    {
      "item": "chisel:limestone|12",
      "emc": 4
    },
    {
      "item": "chisel:limestone|9",
      "emc": 4
    },
    {
      "item": "chisel:limestone|13",
      "emc": 4
    },
    {
      "item": "chisel:limestone|14",
      "emc": 4
    },
    {
      "item": "chisel:limestone|15",
      "emc": 4
    },
    {
      "item": "chisel:limestone1|0",
      "emc": 4
    },
    {
      "item": "chisel:limestone1|1",
      "emc": 4
    },
    {
      "item": "chisel:limestone1|2",
      "emc": 4
    },
    {
      "item": "chisel:limestone1|3",
      "emc": 4
    },
    {
      "item": "chisel:limestone1|4",
      "emc": 4
    },
    {
      "item": "chisel:limestone1|5",
      "emc": 4
    },
    {
      "item": "chisel:limestone1|6",
      "emc": 4
    },
    {
      "item": "chisel:limestone1|7",
      "emc": 4
    },
    {
      "item": "chisel:limestone1|8",
      "emc": 4
    },
    {
      "item": "chisel:limestone1|9",
      "emc": 4
    },
    {
      "item": "chisel:limestone2|0",
      "emc": 4
    },
    {
      "item": "chisel:limestone2|1",
      "emc": 4
    },
    {
      "item": "chisel:limestone2|2",
      "emc": 4
    },
    {
      "item": "chisel:limestone2|3",
      "emc": 4
    },
    {
      "item": "chisel:limestone2|4",
      "emc": 4
    },
    {
      "item": "chisel:limestone2|5",
      "emc": 4
    },
    {
      "item": "chisel:limestone2|6",
      "emc": 4
    },
    {
      "item": "chisel:marble|0",
      "emc": 4
    },
    {
      "item": "chisel:marble|1",
      "emc": 4
    },
    {
      "item": "chisel:marble|2",
      "emc": 4
    },
    {
      "item": "chisel:marble|3",
      "emc": 4
    },
    {
      "item": "chisel:marble|4",
      "emc": 4
    },
    {
      "item": "chisel:marble|5",
      "emc": 4
    },
    {
      "item": "chisel:marble|6",
      "emc": 4
    },
    {
      "item": "chisel:marble|7",
      "emc": 4
    },
    {
      "item": "chisel:marble|8",
      "emc": 4
    },
    {
      "item": "chisel:marble|9",
      "emc": 4
    },
    {
      "item": "chisel:marble|10",
      "emc": 4
    },
    {
      "item": "chisel:marble|11",
      "emc": 4
    },
    {
      "item": "chisel:marble|12",
      "emc": 4
    },
    {
      "item": "chisel:marble|13",
      "emc": 4
    },
    {
      "item": "chisel:marble|14",
      "emc": 4
    },
    {
      "item": "chisel:marble|15",
      "emc": 4
    },
    {
      "item": "chisel:marble1|0",
      "emc": 4
    },
    {
      "item": "chisel:marble1|1",
      "emc": 4
    },
    {
      "item": "chisel:marble1|2",
      "emc": 4
    },
    {
      "item": "chisel:marble1|3",
      "emc": 4
    },
    {
      "item": "chisel:marble1|4",
      "emc": 4
    },
    {
      "item": "chisel:marble1|5",
      "emc": 4
    },
    {
      "item": "chisel:marble1|6",
      "emc": 4
    },
    {
      "item": "chisel:marble1|7",
      "emc": 4
    },
    {
      "item": "chisel:marble1|8",
      "emc": 4
    },
    {
      "item": "chisel:marble1|9",
      "emc": 4
    },
    {
      "item": "chisel:marble2|0",
      "emc": 4
    },
    {
      "item": "chisel:marble2|1",
      "emc": 4
    },
    {
      "item": "chisel:marble2|2",
      "emc": 4
    },
    {
      "item": "chisel:marble2|3",
      "emc": 4
    },
    {
      "item": "chisel:marble2|4",
      "emc": 4
    },
    {
      "item": "chisel:marble2|5",
      "emc": 4
    },
    {
      "item": "chisel:marble2|6",
      "emc": 4
    },
    {
      "item": "chisel:marblepillar|1",
      "emc": 4
    },
    {
      "item": "chisel:marblepillar|0",
      "emc": 4
    },
    {
      "item": "chisel:marblepillar|2",
      "emc": 4
    },
    {
      "item": "chisel:marblepillar|3",
      "emc": 4
    },
    {
      "item": "chisel:marblepillar|4",
      "emc": 4
    },
    {
      "item": "chisel:marblepillar|5",
      "emc": 4
    },
    {
      "item": "chisel:marblepillar|6",
      "emc": 4
    },
    {
      "item": "chisel:marblepillar|7",
      "emc": 4
    },
    {
      "item": "chisel:marblepillar|8",
      "emc": 4
    },
    {
      "item": "chisel:marblepillar|9",
      "emc": 4
    },
    {
      "item": "chisel:marblepillar|10",
      "emc": 4
    },
    {
      "item": "chisel:marblepillar|11",
      "emc": 4
    },
    {
      "item": "chisel:marblepillar|12",
      "emc": 4
    },
    {
      "item": "chisel:marblepillar|13",
      "emc": 4
    },
    {
      "item": "chisel:marblepillar|14",
      "emc": 4
    },
    {
      "item": "chisel:marblepillar|15",
      "emc": 4
    },
    {
      "item": "chisel:netherbrick|0",
      "emc": 4
    },
    {
      "item": "chisel:netherbrick|1",
      "emc": 4
    },
    {
      "item": "chisel:netherbrick|2",
      "emc": 4
    },
    {
      "item": "chisel:netherbrick|3",
      "emc": 4
    },
    {
      "item": "chisel:netherbrick|4",
      "emc": 4
    },
    {
      "item": "chisel:netherbrick|5",
      "emc": 4
    },
    {
      "item": "chisel:netherbrick|6",
      "emc": 4
    },
    {
      "item": "chisel:netherbrick|7",
      "emc": 4
    },
    {
      "item": "chisel:netherbrick|8",
      "emc": 4
    },
    {
      "item": "chisel:netherbrick|9",
      "emc": 4
    },
    {
      "item": "chisel:netherbrick|10",
      "emc": 4
    },
    {
      "item": "chisel:netherbrick|11",
      "emc": 4
    },
    {
      "item": "chisel:netherbrick|12",
      "emc": 4
    },
    {
      "item": "chisel:netherbrick|13",
      "emc": 4
    },
    {
      "item": "chisel:netherbrick|14",
      "emc": 4
    },
    {
      "item": "chisel:netherbrick|15",
      "emc": 4
    },
    {
      "item": "chisel:netherrack|0",
      "emc": 1
    },
    {
      "item": "chisel:netherrack|1",
      "emc": 1
    },
    {
      "item": "chisel:netherrack|2",
      "emc": 1
    },
    {
      "item": "chisel:netherrack|3",
      "emc": 1
    },
    {
      "item": "chisel:netherrack|4",
      "emc": 1
    },
    {
      "item": "chisel:netherrack|5",
      "emc": 1
    },
    {
      "item": "chisel:netherrack|6",
      "emc": 1
    },
    {
      "item": "chisel:netherrack|7",
      "emc": 1
    },
    {
      "item": "chisel:netherrack|8",
      "emc": 1
    },
    {
      "item": "chisel:netherrack|9",
      "emc": 1
    },
    {
      "item": "chisel:netherrack|10",
      "emc": 1
    },
    {
      "item": "chisel:netherrack|11",
      "emc": 1
    },
    {
      "item": "chisel:netherrack|12",
      "emc": 1
    },
    {
      "item": "chisel:netherrack|13",
      "emc": 1
    },
    {
      "item": "chisel:blocknickel|0",
      "emc": 9216
    },
    {
      "item": "chisel:blocknickel|1",
      "emc": 9216
    },
    {
      "item": "chisel:blocknickel|2",
      "emc": 9216
    },
    {
      "item": "chisel:blocknickel|3",
      "emc": 9216
    },
    {
      "item": "chisel:blocknickel|4",
      "emc": 9216
    },
    {
      "item": "chisel:blocknickel|5",
      "emc": 9216
    },
    {
      "item": "chisel:blocknickel|6",
      "emc": 9216
    },
    {
      "item": "chisel:obsidian|0",
      "emc": 64
    },
    {
      "item": "chisel:obsidian|1",
      "emc": 64
    },
    {
      "item": "chisel:obsidian|2",
      "emc": 64
    },
    {
      "item": "chisel:obsidian|3",
      "emc": 64
    },
    {
      "item": "chisel:obsidian|4",
      "emc": 64
    },
    {
      "item": "chisel:obsidian|5",
      "emc": 64
    },
    {
      "item": "chisel:obsidian|6",
      "emc": 64
    },
    {
      "item": "chisel:obsidian|7",
      "emc": 64
    },
    {
      "item": "chisel:obsidian|8",
      "emc": 64
    },
    {
      "item": "chisel:obsidian|9",
      "emc": 64
    },
    {
      "item": "chisel:obsidian|10",
      "emc": 64
    },
    {
      "item": "chisel:obsidian|11",
      "emc": 64
    },
    {
      "item": "chisel:obsidian|12",
      "emc": 64
    },
    {
      "item": "chisel:obsidian|13",
      "emc": 64
    },
    {
      "item": "chisel:obsidian|14",
      "emc": 64
    },
    {
      "item": "chisel:paper|1",
      "emc": 7
    },
    {
      "item": "chisel:paper|2",
      "emc": 7
    },
    {
      "item": "chisel:paper|3",
      "emc": 7
    },
    {
      "item": "chisel:paper|4",
      "emc": 7
    },
    {
      "item": "chisel:paper|5",
      "emc": 7
    },
    {
      "item": "chisel:paper|6",
      "emc": 7
    },
    {
      "item": "chisel:paper|7",
      "emc": 7
    },
    {
      "item": "chisel:paper|8",
      "emc": 7
    },
    {
      "item": "chisel:blockplatinum|0",
      "emc": 36864
    },
    {
      "item": "chisel:blockplatinum|1",
      "emc": 36864
    },
    {
      "item": "chisel:blockplatinum|2",
      "emc": 36864
    },
    {
      "item": "chisel:blockplatinum|3",
      "emc": 36864
    },
    {
      "item": "chisel:blockplatinum|4",
      "emc": 36864
    },
    {
      "item": "chisel:blockplatinum|5",
      "emc": 36864
    },
    {
      "item": "chisel:blockplatinum|6",
      "emc": 36864
    },
    {
      "item": "chisel:prismarine|0",
      "emc": 576
    },
    {
      "item": "chisel:prismarine|1",
      "emc": 576
    },
    {
      "item": "chisel:prismarine|2",
      "emc": 576
    },
    {
      "item": "chisel:prismarine|3",
      "emc": 576
    },
    {
      "item": "chisel:prismarine|4",
      "emc": 576
    },
    {
      "item": "chisel:prismarine|5",
      "emc": 576
    },
    {
      "item": "chisel:prismarine|6",
      "emc": 576
    },
    {
      "item": "chisel:prismarine|7",
      "emc": 576
    },
    {
      "item": "chisel:prismarine|8",
      "emc": 576
    },
    {
      "item": "chisel:prismarine|9",
      "emc": 576
    },
    {
      "item": "chisel:prismarine|10",
      "emc": 576
    },
    {
      "item": "chisel:prismarine|11",
      "emc": 576
    },
    {
      "item": "chisel:prismarine|12",
      "emc": 576
    },
    {
      "item": "chisel:prismarine|13",
      "emc": 576
    },
    {
      "item": "chisel:prismarine|14",
      "emc": 576
    },
    {
      "item": "chisel:prismarine|15",
      "emc": 576
    },
    {
      "item": "chisel:prismarine1|0",
      "emc": 576
    },
    {
      "item": "chisel:prismarine1|1",
      "emc": 576
    },
    {
      "item": "chisel:prismarine1|2",
      "emc": 576
    },
    {
      "item": "chisel:prismarine1|3",
      "emc": 576
    },
    {
      "item": "chisel:prismarine1|4",
      "emc": 576
    },
    {
      "item": "chisel:prismarine1|5",
      "emc": 576
    },
    {
      "item": "chisel:prismarine1|6",
      "emc": 576
    },
    {
      "item": "chisel:prismarine1|7",
      "emc": 576
    },
    {
      "item": "chisel:prismarine1|8",
      "emc": 576
    },
    {
      "item": "chisel:prismarine1|9",
      "emc": 576
    },
    {
      "item": "chisel:prismarine2|0",
      "emc": 576
    },
    {
      "item": "chisel:prismarine2|1",
      "emc": 576
    },
    {
      "item": "chisel:prismarine2|2",
      "emc": 576
    },
    {
      "item": "chisel:prismarine2|3",
      "emc": 576
    },
    {
      "item": "chisel:prismarine2|4",
      "emc": 576
    },
    {
      "item": "chisel:prismarine2|5",
      "emc": 576
    },
    {
      "item": "chisel:quartz|0",
      "emc": 1024
    },
    {
      "item": "chisel:quartz|1",
      "emc": 1024
    },
    {
      "item": "chisel:quartz|2",
      "emc": 1024
    },
    {
      "item": "chisel:quartz|4",
      "emc": 1024
    },
    {
      "item": "chisel:quartz|3",
      "emc": 1024
    },
    {
      "item": "chisel:quartz|5",
      "emc": 1024
    },
    {
      "item": "chisel:quartz|6",
      "emc": 1024
    },
    {
      "item": "chisel:quartz|7",
      "emc": 1024
    },
    {
      "item": "chisel:quartz|8",
      "emc": 1024
    },
    {
      "item": "chisel:quartz|9",
      "emc": 1024
    },
    {
      "item": "chisel:quartz|10",
      "emc": 1024
    },
    {
      "item": "chisel:quartz|11",
      "emc": 1024
    },
    {
      "item": "chisel:quartz|12",
      "emc": 1024
    },
    {
      "item": "chisel:quartz|13",
      "emc": 1024
    },
    {
      "item": "chisel:quartz|14",
      "emc": 1024
    },
    {
      "item": "chisel:quartz|15",
      "emc": 1024
    },
    {
      "item": "chisel:quartz1|0",
      "emc": 1024
    },
    {
      "item": "chisel:quartz1|1",
      "emc": 1024
    },
    {
      "item": "chisel:quartz1|2",
      "emc": 1024
    },
    {
      "item": "chisel:quartz1|3",
      "emc": 1024
    },
    {
      "item": "chisel:quartz1|4",
      "emc": 1024
    },
    {
      "item": "chisel:quartz1|5",
      "emc": 1024
    },
    {
      "item": "chisel:quartz1|6",
      "emc": 1024
    },
    {
      "item": "chisel:quartz1|7",
      "emc": 1024
    },
    {
      "item": "chisel:quartz1|8",
      "emc": 1024
    },
    {
      "item": "chisel:quartz1|9",
      "emc": 1024
    },
    {
      "item": "chisel:quartz1|10",
      "emc": 1024
    },
    {
      "item": "chisel:quartz1|11",
      "emc": 1024
    },
    {
      "item": "chisel:quartz1|12",
      "emc": 1024
    },
    {
      "item": "chisel:quartz1|13",
      "emc": 1024
    },
    {
      "item": "chisel:quartz1|14",
      "emc": 1024
    },
    {
      "item": "chisel:quartz1|15",
      "emc": 1024
    },
    {
      "item": "chisel:redstone|0",
      "emc": 576
    },
    {
      "item": "chisel:redstone|1",
      "emc": 576
    },
    {
      "item": "chisel:redstone|2",
      "emc": 576
    },
    {
      "item": "chisel:redstone|3",
      "emc": 576
    },
    {
      "item": "chisel:redstone|4",
      "emc": 576
    },
    {
      "item": "chisel:redstone|5",
      "emc": 576
    },
    {
      "item": "chisel:redstone|6",
      "emc": 576
    },
    {
      "item": "chisel:redstone|7",
      "emc": 576
    },
    {
      "item": "chisel:redstone|8",
      "emc": 576
    },
    {
      "item": "chisel:redstone|9",
      "emc": 576
    },
    {
      "item": "chisel:redstone|10",
      "emc": 576
    },
    {
      "item": "chisel:redstone|11",
      "emc": 576
    },
    {
      "item": "chisel:redstone|12",
      "emc": 576
    },
    {
      "item": "chisel:redstone|13",
      "emc": 576
    },
    {
      "item": "chisel:redstone|14",
      "emc": 576
    },
    {
      "item": "chisel:redstone|15",
      "emc": 576
    },
    {
      "item": "chisel:redstone1|0",
      "emc": 576
    },
    {
      "item": "chisel:redstone1|1",
      "emc": 576
    },
    {
      "item": "chisel:redstone1|2",
      "emc": 576
    },
    {
      "item": "chisel:redstone1|3",
      "emc": 576
    },
    {
      "item": "chisel:redstone1|4",
      "emc": 576
    },
    {
      "item": "chisel:redstone1|5",
      "emc": 576
    },
    {
      "item": "chisel:redstone1|6",
      "emc": 576
    },
    {
      "item": "chisel:redstone1|7",
      "emc": 576
    },
    {
      "item": "chisel:redstone1|8",
      "emc": 576
    },
    {
      "item": "chisel:redstone1|9",
      "emc": 576
    },
    {
      "item": "chisel:redstone1|10",
      "emc": 576
    },
    {
      "item": "chisel:redstone1|11",
      "emc": 576
    }
  ]
}
